{
  "version": "6.0",
  "nxVersion": "17.1.3",
  "deps": {
    "@angular/animations": "^17.0.2",
    "@angular/common": "^17.0.2",
    "@angular/compiler": "^17.0.2",
    "@angular/core": "^17.0.2",
    "@angular/forms": "^17.0.2",
    "@angular/platform-browser": "^17.0.2",
    "@angular/platform-browser-dynamic": "^17.0.2",
    "@angular/router": "^17.0.2",
    "@capacitor/app": "5.0.6",
    "@capacitor/core": "5.5.1",
    "@capacitor/haptics": "5.0.6",
    "@capacitor/keyboard": "5.0.6",
    "@capacitor/status-bar": "5.0.6",
    "@ionic/angular": "^7.0.0",
    "ionicons": "^7.0.0",
    "rxjs": "~7.8.0",
    "tslib": "^2.3.0",
    "zone.js": "~0.14.2",
    "@angular-devkit/build-angular": "^17.0.0",
    "@angular-eslint/builder": "^17.0.0",
    "@angular-eslint/eslint-plugin": "^17.0.0",
    "@angular-eslint/eslint-plugin-template": "^17.0.0",
    "@angular-eslint/schematics": "^17.0.0",
    "@angular-eslint/template-parser": "^17.0.0",
    "@angular/cli": "^17.0.0",
    "@angular/compiler-cli": "^17.0.2",
    "@angular/language-service": "^17.0.2",
    "@capacitor/cli": "5.5.1",
    "@ionic/angular-toolkit": "^9.0.0",
    "@types/jasmine": "~5.1.0",
    "@typescript-eslint/eslint-plugin": "^6.0.0",
    "@typescript-eslint/parser": "^6.0.0",
    "eslint": "^7.26.0",
    "eslint-plugin-import": "2.22.1",
    "eslint-plugin-jsdoc": "30.7.6",
    "eslint-plugin-prefer-arrow": "1.2.2",
    "jasmine-core": "~5.1.0",
    "jasmine-spec-reporter": "~5.0.0",
    "karma": "~6.4.0",
    "karma-chrome-launcher": "~3.2.0",
    "karma-coverage": "~2.2.0",
    "karma-jasmine": "~5.1.0",
    "karma-jasmine-html-reporter": "~2.1.0",
    "ts-node": "^8.3.0",
    "typescript": "~5.2.2"
  },
  "pathMappings": {},
  "nxJsonPlugins": [],
  "fileMap": {
    "projectFileMap": {},
    "nonProjectFiles": [
      {
        "file": ".angular/cache/17.0.5/angular-webpack/1445aeae9badc66b02955772edd91ee7a548d613/0.pack",
        "hash": "15001846299456801954"
      },
      {
        "file": ".angular/cache/17.0.5/angular-webpack/1445aeae9badc66b02955772edd91ee7a548d613/1.pack",
        "hash": "16097181037478020204"
      },
      {
        "file": ".angular/cache/17.0.5/angular-webpack/1445aeae9badc66b02955772edd91ee7a548d613/10.pack",
        "hash": "13450340732038781517"
      },
      {
        "file": ".angular/cache/17.0.5/angular-webpack/1445aeae9badc66b02955772edd91ee7a548d613/11.pack",
        "hash": "5973288815862680376"
      },
      {
        "file": ".angular/cache/17.0.5/angular-webpack/1445aeae9badc66b02955772edd91ee7a548d613/12.pack",
        "hash": "16749892523899052544"
      },
      {
        "file": ".angular/cache/17.0.5/angular-webpack/1445aeae9badc66b02955772edd91ee7a548d613/2.pack",
        "hash": "17307298240123886124"
      },
      {
        "file": ".angular/cache/17.0.5/angular-webpack/1445aeae9badc66b02955772edd91ee7a548d613/3.pack",
        "hash": "6720372796214261363"
      },
      {
        "file": ".angular/cache/17.0.5/angular-webpack/1445aeae9badc66b02955772edd91ee7a548d613/4.pack",
        "hash": "5060618399640009016"
      },
      {
        "file": ".angular/cache/17.0.5/angular-webpack/1445aeae9badc66b02955772edd91ee7a548d613/5.pack",
        "hash": "9573422629199245325"
      },
      {
        "file": ".angular/cache/17.0.5/angular-webpack/1445aeae9badc66b02955772edd91ee7a548d613/6.pack",
        "hash": "8890274795917187257"
      },
      {
        "file": ".angular/cache/17.0.5/angular-webpack/1445aeae9badc66b02955772edd91ee7a548d613/7.pack",
        "hash": "9520414397042590788"
      },
      {
        "file": ".angular/cache/17.0.5/angular-webpack/1445aeae9badc66b02955772edd91ee7a548d613/8.pack",
        "hash": "17121544691990612218"
      },
      {
        "file": ".angular/cache/17.0.5/angular-webpack/1445aeae9badc66b02955772edd91ee7a548d613/9.pack",
        "hash": "9216300588750665223"
      },
      {
        "file": ".angular/cache/17.0.5/angular-webpack/1445aeae9badc66b02955772edd91ee7a548d613/index.pack",
        "hash": "4526349381174286493"
      },
      {
        "file": ".angular/cache/17.0.5/angular-webpack/1445aeae9badc66b02955772edd91ee7a548d613/index.pack.old",
        "hash": "11878311496162528813"
      },
      {
        "file": ".angular/cache/17.0.5/angular-webpack/187c9463c718af8657be21106183c1877c8a5a58/0.pack",
        "hash": "6160833379351313407"
      },
      {
        "file": ".angular/cache/17.0.5/angular-webpack/187c9463c718af8657be21106183c1877c8a5a58/1.pack",
        "hash": "12791026112222227386"
      },
      {
        "file": ".angular/cache/17.0.5/angular-webpack/187c9463c718af8657be21106183c1877c8a5a58/10.pack",
        "hash": "7289334313359593740"
      },
      {
        "file": ".angular/cache/17.0.5/angular-webpack/187c9463c718af8657be21106183c1877c8a5a58/11.pack",
        "hash": "5756304938236540982"
      },
      {
        "file": ".angular/cache/17.0.5/angular-webpack/187c9463c718af8657be21106183c1877c8a5a58/12.pack",
        "hash": "13592859974689478905"
      },
      {
        "file": ".angular/cache/17.0.5/angular-webpack/187c9463c718af8657be21106183c1877c8a5a58/13.pack",
        "hash": "12465116465839865915"
      },
      {
        "file": ".angular/cache/17.0.5/angular-webpack/187c9463c718af8657be21106183c1877c8a5a58/14.pack",
        "hash": "14183088558101565472"
      },
      {
        "file": ".angular/cache/17.0.5/angular-webpack/187c9463c718af8657be21106183c1877c8a5a58/2.pack",
        "hash": "6838895674282576953"
      },
      {
        "file": ".angular/cache/17.0.5/angular-webpack/187c9463c718af8657be21106183c1877c8a5a58/3.pack",
        "hash": "8796743412264817269"
      },
      {
        "file": ".angular/cache/17.0.5/angular-webpack/187c9463c718af8657be21106183c1877c8a5a58/4.pack",
        "hash": "6298431518847136773"
      },
      {
        "file": ".angular/cache/17.0.5/angular-webpack/187c9463c718af8657be21106183c1877c8a5a58/5.pack",
        "hash": "4402856346675393524"
      },
      {
        "file": ".angular/cache/17.0.5/angular-webpack/187c9463c718af8657be21106183c1877c8a5a58/6.pack",
        "hash": "18004511473401618793"
      },
      {
        "file": ".angular/cache/17.0.5/angular-webpack/187c9463c718af8657be21106183c1877c8a5a58/7.pack",
        "hash": "12955168804515956950"
      },
      {
        "file": ".angular/cache/17.0.5/angular-webpack/187c9463c718af8657be21106183c1877c8a5a58/8.pack",
        "hash": "5780604528659744638"
      },
      {
        "file": ".angular/cache/17.0.5/angular-webpack/187c9463c718af8657be21106183c1877c8a5a58/9.pack",
        "hash": "16813983180159926611"
      },
      {
        "file": ".angular/cache/17.0.5/angular-webpack/187c9463c718af8657be21106183c1877c8a5a58/index.pack",
        "hash": "1393437666199482639"
      },
      {
        "file": ".angular/cache/17.0.5/angular-webpack/187c9463c718af8657be21106183c1877c8a5a58/index.pack.old",
        "hash": "93690329067542970"
      },
      {
        "file": ".angular/cache/17.0.5/angular-webpack/edf2142eebd3dd869f3df4c9d9ce941392015aa9/0.pack",
        "hash": "14349113211616431948"
      },
      {
        "file": ".angular/cache/17.0.5/angular-webpack/edf2142eebd3dd869f3df4c9d9ce941392015aa9/index.pack",
        "hash": "9499539659119791584"
      },
      {
        "file": ".angular/cache/17.0.5/babel-webpack/004b74a9c8708b5e2902527a1d429ae9ebbe63e992b399ae792bbe8c6fe31d8f.json",
        "hash": "4016733503516437701"
      },
      {
        "file": ".angular/cache/17.0.5/babel-webpack/02ab92741130c7221807925ea9a986a2c4cba19b36f50147cd4d0230bcb9cbaa.json",
        "hash": "5845517220184392134"
      },
      {
        "file": ".angular/cache/17.0.5/babel-webpack/02c00f97f934ff46b755a8572fcaea88449404bd4dfe5973b80d3c3d012e5881.json",
        "hash": "12503708796085280498"
      },
      {
        "file": ".angular/cache/17.0.5/babel-webpack/032b602c29592a7b6f309e36e2bd449d61df46a8fabf2e5b4a230548bdd796b3.json",
        "hash": "9189885385200003713"
      },
      {
        "file": ".angular/cache/17.0.5/babel-webpack/0337568702832f18a4e9c1ed93bf2d3992f45fdf16b2f14d90787215cc39fdc8.json",
        "hash": "12525283253316882206"
      },
      {
        "file": ".angular/cache/17.0.5/babel-webpack/04a882a6d0f73b5b92af8e83f8763fcb7afd4d1a0b55aac2c1c7eda574601ba8.json",
        "hash": "6139384617483751718"
      },
      {
        "file": ".angular/cache/17.0.5/babel-webpack/04b99333708db2955e8754134247ca83a4e13d22f1c8a172b5d222187a06670a.json",
        "hash": "6056366703670945075"
      },
      {
        "file": ".angular/cache/17.0.5/babel-webpack/056b8c30c53c8d92a70dd79950402d97c5682469e3f0019cdfca491814800077.json",
        "hash": "14533491209339261058"
      },
      {
        "file": ".angular/cache/17.0.5/babel-webpack/05879038f47013e519b09cd03ee812b8da3b4b64c5f9b8dc8045c0054b635ec3.json",
        "hash": "11841569916318232097"
      },
      {
        "file": ".angular/cache/17.0.5/babel-webpack/06785a9ac1499b5a46a6181e8c2cfa2832a9fd91873f35ff829ca1ccc2433605.json",
        "hash": "11120454289856917133"
      },
      {
        "file": ".angular/cache/17.0.5/babel-webpack/06db6750853eb619696d5e62a17f16a5de39987b0d4dc83204c81f18a8fb850d.json",
        "hash": "153708838158376738"
      },
      {
        "file": ".angular/cache/17.0.5/babel-webpack/07137ad865e21b8226c4694e5374744e5f761502bff1cfbea8026cb48f6b6560.json",
        "hash": "18414754353790921711"
      },
      {
        "file": ".angular/cache/17.0.5/babel-webpack/07bf43a8aef2e9096d380fdafd01358a0793d30b347e91cf318d5241690f076c.json",
        "hash": "9020093111111827477"
      },
      {
        "file": ".angular/cache/17.0.5/babel-webpack/08932bd00a1bbdcd17a3be4395fc703601818d9a87c2e61ffd77b575ba5e8ff5.json",
        "hash": "5440398942177227801"
      },
      {
        "file": ".angular/cache/17.0.5/babel-webpack/08a842b36eb797a8a4a9127553d156d48f6f89bcda02b66782c0e8e3c9a56c30.json",
        "hash": "6452512527066281369"
      },
      {
        "file": ".angular/cache/17.0.5/babel-webpack/0948a95f646fb2942a91a6a8f60666d07b1b0325531ceda80265d3b47b8a5caa.json",
        "hash": "7626393631957211692"
      },
      {
        "file": ".angular/cache/17.0.5/babel-webpack/098a3d9414c9fd33ec09c4c6630da0711400dd3709f09f3cbb0bb2eb0b04bcc2.json",
        "hash": "15147067342175161940"
      },
      {
        "file": ".angular/cache/17.0.5/babel-webpack/0aa7a6eb591a31b84a8c14f7521a3a32b76b86b8343844a9e9a8edc774223b2b.json",
        "hash": "8624231775935055883"
      },
      {
        "file": ".angular/cache/17.0.5/babel-webpack/0aef2e6524c4af090e34423c4a7d6dfa821b8feb2f7fe6d559ec8c4e2574ced7.json",
        "hash": "4971633267979255431"
      },
      {
        "file": ".angular/cache/17.0.5/babel-webpack/0b1232afb84be064ef667579d8dd39c2866254c54cff9801c95df3793adb46ba.json",
        "hash": "5821817706658607301"
      },
      {
        "file": ".angular/cache/17.0.5/babel-webpack/0cd4842ff90d849a657824d7d9fa6b30efa10d7a22c42f54750287b0da7a8265.json",
        "hash": "17368949338344991177"
      },
      {
        "file": ".angular/cache/17.0.5/babel-webpack/0d07d65688b9c955cb3e1b523ee93fd786fd0f7f2d00fc3f01fa663ee06c33e4.json",
        "hash": "14774140257737038938"
      },
      {
        "file": ".angular/cache/17.0.5/babel-webpack/0d32fff2647aaf09c9d24f22d0ab9ec47c9e5c25087aeadee43f71d390209321.json",
        "hash": "18207857857043069498"
      },
      {
        "file": ".angular/cache/17.0.5/babel-webpack/0ebab1ff9fc5237b2fcbe2188c414e1069c75c4453fcac10335b4746c30a5eb3.json",
        "hash": "353155573331507058"
      },
      {
        "file": ".angular/cache/17.0.5/babel-webpack/0faf6f5f28825265beba0ba8a15ebd9f2e149b6dd024125d1d30785da14a04a3.json",
        "hash": "18232386021940403592"
      },
      {
        "file": ".angular/cache/17.0.5/babel-webpack/1013787bef392bd9d1c3d07b7a853d2ccc927d7d9d5ef22335a0c768fc08bc42.json",
        "hash": "8409586087677224838"
      },
      {
        "file": ".angular/cache/17.0.5/babel-webpack/106a28b8995cbb019a05634e013c83709b1dd046f210c3f42259564c1179b404.json",
        "hash": "8698438439900753699"
      },
      {
        "file": ".angular/cache/17.0.5/babel-webpack/1099e8bb59e4879397c0bb3ded7f4fc6209471cd2d267bc4e94bbf916628ffe5.json",
        "hash": "6425314937992511065"
      },
      {
        "file": ".angular/cache/17.0.5/babel-webpack/10b02fc2933520e1dceac34a6e2d96fb15946a9c01517507d2ea1a422606376a.json",
        "hash": "14195612247786997247"
      },
      {
        "file": ".angular/cache/17.0.5/babel-webpack/10cf4b36fe71de250a7b63324f0d3abedfbb3a8a1a35bfd431965a09a0d96386.json",
        "hash": "17056588292174249983"
      },
      {
        "file": ".angular/cache/17.0.5/babel-webpack/11d4b1f7e74c27a0e7d04304fa46dc5098c03ff27f79dc701fcc9079288694b1.json",
        "hash": "4131658374448762627"
      },
      {
        "file": ".angular/cache/17.0.5/babel-webpack/12153be73be20cd936b4f4f400524b3044027071b7538f6ede8afa7577acb951.json",
        "hash": "14647263424055226579"
      },
      {
        "file": ".angular/cache/17.0.5/babel-webpack/128caf34955fead97de2dfd6ec09665c6860e672e175a3cd00e22a3c18eb216c.json",
        "hash": "3333773139779226861"
      },
      {
        "file": ".angular/cache/17.0.5/babel-webpack/129c57b77c31e5cb36784c3edaf8d4835e1a800c629a3fc0a99f491a6eaa9971.json",
        "hash": "7231243117543661685"
      },
      {
        "file": ".angular/cache/17.0.5/babel-webpack/134910cfa3e564b0e9a7988665b15d1c39642c6885e2634289d82fe895cedcb0.json",
        "hash": "14917392795067438008"
      },
      {
        "file": ".angular/cache/17.0.5/babel-webpack/144729fe093cdd314ea25268d72be18bf03fdbdf290c6c2f12a7743d2ca7638d.json",
        "hash": "7034551312076657612"
      },
      {
        "file": ".angular/cache/17.0.5/babel-webpack/1497b116ed051af4adecb6e1b4eee3491f387619d068781ee67b4a94785bc64a.json",
        "hash": "14393340170754726886"
      },
      {
        "file": ".angular/cache/17.0.5/babel-webpack/14d875188807978b4e7c868d33e1fdf34f5ae87cba8c5007b3c8a5f76ce24cb1.json",
        "hash": "13207347133018066881"
      },
      {
        "file": ".angular/cache/17.0.5/babel-webpack/150c654887ea7b9a6955b8ce007166af7e07eb7ca79c318fe4f24065fb79ce72.json",
        "hash": "12026505481122255611"
      },
      {
        "file": ".angular/cache/17.0.5/babel-webpack/16b5bcc2d7e12809e9a0740d474963cbd32922461b1c77f4798bda9c4d755f31.json",
        "hash": "12219929956687498630"
      },
      {
        "file": ".angular/cache/17.0.5/babel-webpack/16c74c77d0f2d27067e7c7ede49d66d25fae56446b9bf087cfd1294b1de0e5ef.json",
        "hash": "16850354573621076329"
      },
      {
        "file": ".angular/cache/17.0.5/babel-webpack/17b2bd2f50f7e266ee5eda60b22c43b047638b612698f06fc463fb59222bbe3c.json",
        "hash": "14997013879690755299"
      },
      {
        "file": ".angular/cache/17.0.5/babel-webpack/17d0a3017538ed4fa66220bff551b9a8a20426b194a9bfea6438468927a4427b.json",
        "hash": "5819163749236037736"
      },
      {
        "file": ".angular/cache/17.0.5/babel-webpack/1858075308f76b640dc55c9faf1b41a7cafedb6326758c982202b68dcf0b0328.json",
        "hash": "4895448747635729855"
      },
      {
        "file": ".angular/cache/17.0.5/babel-webpack/18745dbe6d5be6f543a1ff878f0c70ba8cdf19e1616f6305da9e9e288a846db3.json",
        "hash": "5949755754842655715"
      },
      {
        "file": ".angular/cache/17.0.5/babel-webpack/19754b90d729f42e5675b2025925db1d5869d02b1ba28fe1fdbb8b7cdb63f67f.json",
        "hash": "5786443751287697967"
      },
      {
        "file": ".angular/cache/17.0.5/babel-webpack/1a235bdb58d63ae89d69a341a8f7209b51e25f37f67347b8f769a11384cdf7b0.json",
        "hash": "13682907119989244367"
      },
      {
        "file": ".angular/cache/17.0.5/babel-webpack/1bba5b00d46d84fb55aa10fc26bdfe8ffea1e0e6b36187010be419e148f226f9.json",
        "hash": "1330301667281043521"
      },
      {
        "file": ".angular/cache/17.0.5/babel-webpack/1bc367937c7eb893e422612bb2225057f52ee5335386b050b2395d769a386a42.json",
        "hash": "9163603133087232802"
      },
      {
        "file": ".angular/cache/17.0.5/babel-webpack/1ce88300f8b19be33c9cc869567241462a337759983b1bd59eb3ab7cc20f63aa.json",
        "hash": "8266121291520536973"
      },
      {
        "file": ".angular/cache/17.0.5/babel-webpack/1d15e241fb14b7a17ae584abc4631a6c936635d96a89998ef391ba4f8dc70d74.json",
        "hash": "13788981639079195303"
      },
      {
        "file": ".angular/cache/17.0.5/babel-webpack/1d2de3cb51dbfd0592f5e2b6a9c360ebb6da5d65a421807a21bdbb6ddd43413c.json",
        "hash": "16023008747386928058"
      },
      {
        "file": ".angular/cache/17.0.5/babel-webpack/1d686556ac01326ba62e19263ac366e85cd764a370cd4a115e4689372a52d67b.json",
        "hash": "11373746245736501652"
      },
      {
        "file": ".angular/cache/17.0.5/babel-webpack/1da7d0a83655738406eaa6b9fa5f6706d65528008cf650478abe61cd74d4c515.json",
        "hash": "6947739178398621465"
      },
      {
        "file": ".angular/cache/17.0.5/babel-webpack/1f28faad5941eccb3644aaafc7eefe182bef6d9c69cbba6b2e834e2a7eaf77ef.json",
        "hash": "9423486988111017928"
      },
      {
        "file": ".angular/cache/17.0.5/babel-webpack/1f530ce5d70014dcd710bf160b8e77351c005196a26716baff1b3e0f0726b6b6.json",
        "hash": "10212191083793848968"
      },
      {
        "file": ".angular/cache/17.0.5/babel-webpack/1fac86d0c95d40fe1f2a4a5ab4ccc058787547231eed0a0924861dafbd1544da.json",
        "hash": "16959539652461525098"
      },
      {
        "file": ".angular/cache/17.0.5/babel-webpack/1fc51e1422fb530ae7003d9a5b0c53aad333f9c6444d7521185a1178b2189021.json",
        "hash": "13703237532892264034"
      },
      {
        "file": ".angular/cache/17.0.5/babel-webpack/210d06f41bd541eb1653d60e142130ab1c09c8385ae2da5f6f2f732a54037b85.json",
        "hash": "2543160907853380728"
      },
      {
        "file": ".angular/cache/17.0.5/babel-webpack/22398def05ef070f9e184ae04f03bb004b22a8100f25e57973f26d2efe172e0b.json",
        "hash": "769136224524931100"
      },
      {
        "file": ".angular/cache/17.0.5/babel-webpack/224891d60c5f7b58ebe25456e1353b5a422bd5059c91c152d7ad47c35050ae03.json",
        "hash": "2899150620977626890"
      },
      {
        "file": ".angular/cache/17.0.5/babel-webpack/22a5147f8a30acdbaaa3c74b633cd1aa5c5cdb33d6688ca4fae02c5dcef247cb.json",
        "hash": "2102741461758268085"
      },
      {
        "file": ".angular/cache/17.0.5/babel-webpack/22d334e33367975911fa02c908986becc36895d3d8097c6d74ef1050d227d39f.json",
        "hash": "4228826808434482911"
      },
      {
        "file": ".angular/cache/17.0.5/babel-webpack/237e7bd1f02291dd45b54969a4509dd394d07e64baf853e38506922f970ee63d.json",
        "hash": "8249459148797767550"
      },
      {
        "file": ".angular/cache/17.0.5/babel-webpack/23abe9676a2a289d6ecce043b3836a94d6e0d6994591d9442966ace15c280ae4.json",
        "hash": "15411389087380674308"
      },
      {
        "file": ".angular/cache/17.0.5/babel-webpack/23acec206d0aa9883b9a4e39394c281ee42916620cd1a08b6a8773b5580b3e03.json",
        "hash": "3613064327352175217"
      },
      {
        "file": ".angular/cache/17.0.5/babel-webpack/258dd3d90cc72152fe53c1e995a18d5561d049b6933e8c1429871b53afeef2b9.json",
        "hash": "16604382713298920702"
      },
      {
        "file": ".angular/cache/17.0.5/babel-webpack/267189b09cd78aac1fb6d34107a2d1c2ab2272f8814f6fdbdc67a5f39b56ee53.json",
        "hash": "7175246003834874808"
      },
      {
        "file": ".angular/cache/17.0.5/babel-webpack/2701dcf01f0d57c17ead876e7cb1464e420f3b48a0f4915b5adcf728995cca9f.json",
        "hash": "15449190703645902259"
      },
      {
        "file": ".angular/cache/17.0.5/babel-webpack/2827aa08cd9e50a22f527185a11f2a9fe5a3876b38d31709cdec2b53a3e82306.json",
        "hash": "11416378962071669745"
      },
      {
        "file": ".angular/cache/17.0.5/babel-webpack/2a4ff64adadd2a866cf3c56885cbb5c17dad6333921c7a8427c8e71aa5ec0908.json",
        "hash": "5632437363297182507"
      },
      {
        "file": ".angular/cache/17.0.5/babel-webpack/2ae52d11557a1bd74453e63a2a9f850685ecf4afa8b9a22828a0f3981b450616.json",
        "hash": "14602446141962645028"
      },
      {
        "file": ".angular/cache/17.0.5/babel-webpack/2bb9a1b05c78502a706c094eacd3d9a3be9d69e1ce193bc6f8b0a62fff11abd6.json",
        "hash": "9137450922549118702"
      },
      {
        "file": ".angular/cache/17.0.5/babel-webpack/2cfc7aa451b654a69cf505e117684081719ed776ccc041ba2025b0a3867e837a.json",
        "hash": "3194626246022836664"
      },
      {
        "file": ".angular/cache/17.0.5/babel-webpack/2de9ae13b3152c2b2f844f3d1835de2a0b7590b8d95968c3a6a9f60e0766db55.json",
        "hash": "876737229634892536"
      },
      {
        "file": ".angular/cache/17.0.5/babel-webpack/2e68248f6ef4b0202d4fed42a14a7b17a9995585a92a25c66486c214411fd28d.json",
        "hash": "7648250049464109111"
      },
      {
        "file": ".angular/cache/17.0.5/babel-webpack/300185f8be45176a3e9256c522c203228290417017d0ccf22c2fce0ce77a416e.json",
        "hash": "2000279981948370209"
      },
      {
        "file": ".angular/cache/17.0.5/babel-webpack/3105812454dd6e4cf31fe77e7d63b6d07fd199a48720e74b02647e9a5bc1324a.json",
        "hash": "1884783959300725352"
      },
      {
        "file": ".angular/cache/17.0.5/babel-webpack/3123e3b2e84fedc6388e943394ea1eef366b1da400e3e4700ca2e570098f2f67.json",
        "hash": "14678087747056290582"
      },
      {
        "file": ".angular/cache/17.0.5/babel-webpack/333a2b617a9a5250e230e9a9202646d8e53de18c105bc16e57171bf9aa0a470c.json",
        "hash": "16380264891112214361"
      },
      {
        "file": ".angular/cache/17.0.5/babel-webpack/33807cd01df0a492b2f44e2120fbd3e5b7afa004a00bcc6a7b1edef2728901f3.json",
        "hash": "3905543176650113451"
      },
      {
        "file": ".angular/cache/17.0.5/babel-webpack/3480482a802e3b530b9b0218d7d73f988b5c3b18660652cd2d45303f728d5d2f.json",
        "hash": "11503475907143496931"
      },
      {
        "file": ".angular/cache/17.0.5/babel-webpack/3510e95552f251679505e350d62e8bec8d2dcf9e260578965daebf831cb0af68.json",
        "hash": "2813570798839683037"
      },
      {
        "file": ".angular/cache/17.0.5/babel-webpack/361ba7ef5652c7d10f32827445ff67e2d73044f82176f4fae4d1f172f0807317.json",
        "hash": "13823461233716167388"
      },
      {
        "file": ".angular/cache/17.0.5/babel-webpack/36d403bfac75736aed909bb08140c3e5b5c5085d061a7cc59c9b1a737dfbc12e.json",
        "hash": "12579027095799396812"
      },
      {
        "file": ".angular/cache/17.0.5/babel-webpack/37310060b3a91a50ae23f4d5ae378e7c7099c3cce366ca89b7d6c104c6ae7c69.json",
        "hash": "8293948990272744168"
      },
      {
        "file": ".angular/cache/17.0.5/babel-webpack/373b96bc13b9a51ea9715c8fb6461f078bcea1eaddd105afbb4fcbcc0fdcc877.json",
        "hash": "16578808023126605005"
      },
      {
        "file": ".angular/cache/17.0.5/babel-webpack/375053eaf2bf5850ce4b3740d096e96354d891e7f324ffea24db034e150af81f.json",
        "hash": "1957795628183908195"
      },
      {
        "file": ".angular/cache/17.0.5/babel-webpack/3792f4e042f7ab49d54ce4d26b49175c4cf81ad4e8938a795a8a13997aff68e8.json",
        "hash": "6093150843821375598"
      },
      {
        "file": ".angular/cache/17.0.5/babel-webpack/37fcd75657f52a3d047e09fdf4225d94609394eed86de782b39c805e5fd1e4d4.json",
        "hash": "4909705080806178913"
      },
      {
        "file": ".angular/cache/17.0.5/babel-webpack/37fe150e6fb54711eb2e7d67f7886eaadaa3928e2e69746ae1a202a5b7eedd05.json",
        "hash": "1081363880309563244"
      },
      {
        "file": ".angular/cache/17.0.5/babel-webpack/3859335f1ca7ccd71eba54d117473aa5d4b3427f9bc5da9ed0187040a453a930.json",
        "hash": "1556030048529079965"
      },
      {
        "file": ".angular/cache/17.0.5/babel-webpack/387be34ab8860b5a42ff4ead2bc95e64551bd6eeaceef2d8c6ae2966fa65b928.json",
        "hash": "11006740757170092944"
      },
      {
        "file": ".angular/cache/17.0.5/babel-webpack/38992b39e2a89d51fdd0d05406041cb93d2d7a375a900a439a9b3a94c5f6d188.json",
        "hash": "10988026354177155532"
      },
      {
        "file": ".angular/cache/17.0.5/babel-webpack/38aa3da17b7cf548d566e54f235cdd18cade986050b01585562d4da9c03b6353.json",
        "hash": "11654767748560951544"
      },
      {
        "file": ".angular/cache/17.0.5/babel-webpack/399a98346c21b6d9dbb307952ec4829f45a9b5a11a2ac58d6ba13707ef4e17fb.json",
        "hash": "9362806527126289418"
      },
      {
        "file": ".angular/cache/17.0.5/babel-webpack/399ff53e65c6bba1fe2485e489ea30bcdfa0bca5d0a77f441461c1b23413220d.json",
        "hash": "8552168159498879660"
      },
      {
        "file": ".angular/cache/17.0.5/babel-webpack/39c589db79c7e4467bd23dd0194dd2b525e1936fe672ead7dc05d443b31f7e46.json",
        "hash": "2232056447951245483"
      },
      {
        "file": ".angular/cache/17.0.5/babel-webpack/3a493408ff507d5cf438f00280d21742d9bafd74cfe123b1e0c60373e971b99a.json",
        "hash": "8557788782457700700"
      },
      {
        "file": ".angular/cache/17.0.5/babel-webpack/3a6d2c7a0e81879076b46397a0a4bc8848b6bed872a28febd4bb326c3ebcc956.json",
        "hash": "16609462914430547522"
      },
      {
        "file": ".angular/cache/17.0.5/babel-webpack/3bd16622b88fbeff671a9423a9926d6c89dc76b544409fa7dff3d264a3b8b187.json",
        "hash": "992490312182041434"
      },
      {
        "file": ".angular/cache/17.0.5/babel-webpack/3eac2ad16c3af3404ca126298c97809f3c7cf595162c2b81c41974038455d8be.json",
        "hash": "12626957947803976501"
      },
      {
        "file": ".angular/cache/17.0.5/babel-webpack/3f4889a5738dd29d9d042ff05334dc014d143c58e1f34209bb9e46b393939eb5.json",
        "hash": "13956798008768272142"
      },
      {
        "file": ".angular/cache/17.0.5/babel-webpack/404ac2e23048d98f29e9e9b6dda1e4172c55f48680811fb4356fad42baa405e0.json",
        "hash": "4202967456389724024"
      },
      {
        "file": ".angular/cache/17.0.5/babel-webpack/40a6e6ec54eda6e60dc1871eb50fd7ffd164e31570132c7cc5753890868d2a01.json",
        "hash": "13837874428099972366"
      },
      {
        "file": ".angular/cache/17.0.5/babel-webpack/41bd1316f022369bb030e99571998be684bb4da103b011dea124c656b31aca78.json",
        "hash": "2654549481340523894"
      },
      {
        "file": ".angular/cache/17.0.5/babel-webpack/426bf2e34ed05c8f1c0f82883a6f7a62dc1b407ddf33dd356a79644f60820949.json",
        "hash": "6864293100165860607"
      },
      {
        "file": ".angular/cache/17.0.5/babel-webpack/4296117a20a8537ece1072958c487e67bb0f02cc5eeb568a819695373607bf9e.json",
        "hash": "10030924075784269925"
      },
      {
        "file": ".angular/cache/17.0.5/babel-webpack/42f4064ccbfc82c00d7ef14d9e36e9c2afada54ec1a07f7d66f7553f447cf2fa.json",
        "hash": "7050139501057052730"
      },
      {
        "file": ".angular/cache/17.0.5/babel-webpack/4361c5dfb9edc54234a20b123e98a58357bdc65fce5279cf0f84423cb4604533.json",
        "hash": "6159250534217629444"
      },
      {
        "file": ".angular/cache/17.0.5/babel-webpack/44bf7d17b383ba2b0143d6ac252c955f7c587b3fd89ca934399830f3e6f8be11.json",
        "hash": "3428085768902750637"
      },
      {
        "file": ".angular/cache/17.0.5/babel-webpack/4528332da9998336e0685ab7f078af940d5cff385f81054e3d0cabc10ffa793f.json",
        "hash": "10229369753815298097"
      },
      {
        "file": ".angular/cache/17.0.5/babel-webpack/453ac1238d212c0da13e2320617352fd0cc55967df59d67edbd7d63539a961e1.json",
        "hash": "3052774695474751469"
      },
      {
        "file": ".angular/cache/17.0.5/babel-webpack/45453ba06c0a5822c37039c8d74620f6e2d25733664f759764344fd36a09815e.json",
        "hash": "3219705668761417013"
      },
      {
        "file": ".angular/cache/17.0.5/babel-webpack/455bf1c4fc85b23c4da570b6f15c48fd710ebcf449ddb4a27e2e1f5381ce52c8.json",
        "hash": "3199143292414063589"
      },
      {
        "file": ".angular/cache/17.0.5/babel-webpack/461078cf19db7caadc8adf9661eb4426a0f36d4dc0bd8e52213752e1ebc9380a.json",
        "hash": "1818505833576284903"
      },
      {
        "file": ".angular/cache/17.0.5/babel-webpack/46200ed76b173f7e9b77ea803b46af5a056e3cac4264b2d037a07a70440dfda0.json",
        "hash": "16247270952655148306"
      },
      {
        "file": ".angular/cache/17.0.5/babel-webpack/46898114c3c8b274854bc5e6dd6252478f1f8b16c5030419af365b3b3f5470ac.json",
        "hash": "7843114110000071520"
      },
      {
        "file": ".angular/cache/17.0.5/babel-webpack/46bc6802f627a8b7d4a4831830df1a50e79517ab39213a31ecbd646c2a093abc.json",
        "hash": "8452161293148965318"
      },
      {
        "file": ".angular/cache/17.0.5/babel-webpack/470075398713ee21709e0cfd3c6bff187a28e5f2650507d4be71dd0ffeb0ab12.json",
        "hash": "14555518709571972407"
      },
      {
        "file": ".angular/cache/17.0.5/babel-webpack/47f1766832ecf9ef89dad2143786259c4e26ac32887978ba725ed1aa351d02e5.json",
        "hash": "849500370596784883"
      },
      {
        "file": ".angular/cache/17.0.5/babel-webpack/4866a7c8dcf87312002e8ded05910a07ef9b1ed2c278f7071d23d28a00d54e53.json",
        "hash": "8726624203800896745"
      },
      {
        "file": ".angular/cache/17.0.5/babel-webpack/48a93e2580cfaf9c111c3d8e799b53c1613ecccd829b4dc40eaa159ed8c19480.json",
        "hash": "5069343705087249354"
      },
      {
        "file": ".angular/cache/17.0.5/babel-webpack/4946f727d7b81c9f07d4b7f0adc90c921cf9a92897e9df787eb0e7d8a24589f6.json",
        "hash": "9094716247999686003"
      },
      {
        "file": ".angular/cache/17.0.5/babel-webpack/4ab597e2dbbe6c4c0c6e0ee73555f40221225b9615aed6c5d1ece305b2ff186b.json",
        "hash": "9678078068916998230"
      },
      {
        "file": ".angular/cache/17.0.5/babel-webpack/4b1e4cf1e11d9f363b87f29885701ced85ff15558c8ed92c8a9500efef634d26.json",
        "hash": "579291427305116206"
      },
      {
        "file": ".angular/cache/17.0.5/babel-webpack/4d2dbb2bce92cf792674847e37c1df263b83da90141b14cd71f4c2c176970e45.json",
        "hash": "739969862768990309"
      },
      {
        "file": ".angular/cache/17.0.5/babel-webpack/4d552292351cbc2802ac55ab262e955a1fe02f796167a523bf6558d6a5aaae5e.json",
        "hash": "4917396847673966292"
      },
      {
        "file": ".angular/cache/17.0.5/babel-webpack/4d8f5af2d6538c7c2654f2c6a777b91b2d83a9781811b9bc8b436e068920ab1f.json",
        "hash": "12272914115762652489"
      },
      {
        "file": ".angular/cache/17.0.5/babel-webpack/4daabcbfff0816c023bb2d352a0577ef82ed400b9e1d72fc82e8d9215f2e3877.json",
        "hash": "2438347004015097535"
      },
      {
        "file": ".angular/cache/17.0.5/babel-webpack/4dba1ff93db980258e32f44f6cfd0a9be9bc5f7d501fdde051e7eeb72a90877c.json",
        "hash": "17442955034545608552"
      },
      {
        "file": ".angular/cache/17.0.5/babel-webpack/4dcf1fd33734f58723e37adee7485ccde17f261569c8cefed891f35be114ec86.json",
        "hash": "8804132493344154297"
      },
      {
        "file": ".angular/cache/17.0.5/babel-webpack/4dd3b5b20b99634adb33e492d0408b354b456757e0460f2e202542caf2b045f8.json",
        "hash": "10296638760095006147"
      },
      {
        "file": ".angular/cache/17.0.5/babel-webpack/4dd6540e3fe6aa058f5b0307994013d3d469f396cccbd770abe301909d287d13.json",
        "hash": "2519853418395234260"
      },
      {
        "file": ".angular/cache/17.0.5/babel-webpack/4f1893e395da74898f0c6165764d148fd29d65c451710fc8c4ac6e035b27747f.json",
        "hash": "13431979101134692755"
      },
      {
        "file": ".angular/cache/17.0.5/babel-webpack/4f989f9ecd9732ab557e71e3eca8303b8050e5912eff9e3236a3640c6dcde05f.json",
        "hash": "17975568280609438440"
      },
      {
        "file": ".angular/cache/17.0.5/babel-webpack/5103f0ebbd4d5fc7dff9f5efdd4392ff9583f24f5911f0b7009da740d78e7bda.json",
        "hash": "7423206402174197772"
      },
      {
        "file": ".angular/cache/17.0.5/babel-webpack/5122acda139188a6ed5792fabb150a33b0cde66c972e1edba14973944b04fb28.json",
        "hash": "6232089741075553979"
      },
      {
        "file": ".angular/cache/17.0.5/babel-webpack/527dd288c000e5974ac37a47ae40dc22a9efe94b6b9c6ed592bdb4ca45e055d8.json",
        "hash": "14296088717964879450"
      },
      {
        "file": ".angular/cache/17.0.5/babel-webpack/528b1ad7326dac5018a19b850131b2e28ba954e201441f1558bbe4598f47d5e8.json",
        "hash": "8505625442388754305"
      },
      {
        "file": ".angular/cache/17.0.5/babel-webpack/528cbf19079834db23642419b708cfd70893d2fd42ef6b0f264dc101646de662.json",
        "hash": "11578068560013349410"
      },
      {
        "file": ".angular/cache/17.0.5/babel-webpack/52f0c4b711e66f431744c95bd164916dfca23e901e74b97f5bc143d6cb605d02.json",
        "hash": "3419174698650421864"
      },
      {
        "file": ".angular/cache/17.0.5/babel-webpack/5380d7ae4c19d17282a6d887a73fbe9d61f0417d1984777ec022d09e3e66bb76.json",
        "hash": "6277878256215039974"
      },
      {
        "file": ".angular/cache/17.0.5/babel-webpack/54344c582b9780253f2cabaed19127bca22257f503bfa36fb20cebd4dfd8cd03.json",
        "hash": "863168739555539213"
      },
      {
        "file": ".angular/cache/17.0.5/babel-webpack/555acbe0c4a991faa68ea7f22ef7c220fe6fa785db03e6b46b82e9206aa6c92e.json",
        "hash": "2879907380498423104"
      },
      {
        "file": ".angular/cache/17.0.5/babel-webpack/55c29e2269a28fb8ab9666b5029ff912114775e9fda41da423fc51951b8a6931.json",
        "hash": "16172258036484267499"
      },
      {
        "file": ".angular/cache/17.0.5/babel-webpack/55c6ce002f7320aa29fe8127b81e87c56ca2ed9aa94681769e598c6c7c19c3f9.json",
        "hash": "8340488028068975704"
      },
      {
        "file": ".angular/cache/17.0.5/babel-webpack/5649b0bc8e161b0bf3456b385b92254305e158c27c2e9ac67d84649ad3915fe4.json",
        "hash": "7970331386557363049"
      },
      {
        "file": ".angular/cache/17.0.5/babel-webpack/564faa7f375d7d26c958697cdca2f64e7edb8e9ba43d50938c37470b92a6d353.json",
        "hash": "3942859155351884804"
      },
      {
        "file": ".angular/cache/17.0.5/babel-webpack/5775145a061d2ec080afd7fbc26bfde919781ff844b8a1fd5ea0eb28b9fe7b98.json",
        "hash": "12663863093411136343"
      },
      {
        "file": ".angular/cache/17.0.5/babel-webpack/579c57dc7ed623049f901bbd7d1507172adb6eed0316040ba05ae61dd4f54e50.json",
        "hash": "5527655029302659355"
      },
      {
        "file": ".angular/cache/17.0.5/babel-webpack/5923c9849d757397285d8d20422eeed425c23ab2d659218450dbbd657c8f2149.json",
        "hash": "5644434283243460329"
      },
      {
        "file": ".angular/cache/17.0.5/babel-webpack/59be5ac35f2ab90c2801f0757ed76e298d749bd8db95fffd990c09bb5e0ddc3a.json",
        "hash": "17592451121806351116"
      },
      {
        "file": ".angular/cache/17.0.5/babel-webpack/59c05540aad6b3e3f3c0af1a9ed1c97776b27138f066fc79ccda6183517a38b4.json",
        "hash": "17440257858627509549"
      },
      {
        "file": ".angular/cache/17.0.5/babel-webpack/59e635e47cb1a9d949ab6563010aebdd456caad739c78b943fe436cf84fe5812.json",
        "hash": "8132904259903200154"
      },
      {
        "file": ".angular/cache/17.0.5/babel-webpack/5a99427fb88e5ae4a9f41a2c49ce0a04637e1713827c3df6d4970f18a500cab1.json",
        "hash": "11736126017309351841"
      },
      {
        "file": ".angular/cache/17.0.5/babel-webpack/5b1f9819714dd0a6d6c906aee411c5b13fafb1e59ec5861e14afe7501c322144.json",
        "hash": "6366396956738889049"
      },
      {
        "file": ".angular/cache/17.0.5/babel-webpack/5b2c23ca46b19aa32457064d0af2b0c18de1a0c86cd5f05645843d9709f8e621.json",
        "hash": "7650798568759127691"
      },
      {
        "file": ".angular/cache/17.0.5/babel-webpack/5bcf40686e7efb211baf11acf8a0178951f7a2fc6eb53a03b839635b1e00c5a7.json",
        "hash": "18419741403212129451"
      },
      {
        "file": ".angular/cache/17.0.5/babel-webpack/5c58e4ce33880aace057dc8d83b2630e0b836112121a889f3b04e2021945413c.json",
        "hash": "4508664638237327191"
      },
      {
        "file": ".angular/cache/17.0.5/babel-webpack/5d943adc96d7b490c7fbad9f399a921a3341b80ce60d3c4f90fb9b042eef8348.json",
        "hash": "10185978466959843075"
      },
      {
        "file": ".angular/cache/17.0.5/babel-webpack/5dab841b45e3d710717a55d322914c9625a5710642911c07315e05955c00256e.json",
        "hash": "4453672573216680742"
      },
      {
        "file": ".angular/cache/17.0.5/babel-webpack/5faf56cf8a3524ee774fad93ef71ab22114e6623529d7924a918b3793d8854d9.json",
        "hash": "10544351076008145145"
      },
      {
        "file": ".angular/cache/17.0.5/babel-webpack/5fc722470d8cd9183fd10e27f109a2d461301cdb73abf9159d5afa9e6ebbf8a9.json",
        "hash": "5267004456027036166"
      },
      {
        "file": ".angular/cache/17.0.5/babel-webpack/6019f7d636151ba6da1bbc2e1e351c90a710323826b71b89f3be13e18a3f8750.json",
        "hash": "10705787886025068400"
      },
      {
        "file": ".angular/cache/17.0.5/babel-webpack/6132c122f6f12e5ca49d89414dab77d846ea7f21ff8ab060280fa0a3e309b108.json",
        "hash": "8159286575430534689"
      },
      {
        "file": ".angular/cache/17.0.5/babel-webpack/61b03881c1a14dc2dfaf3d571951b933498a7bd1e162db07150a2597e0e293af.json",
        "hash": "15632087029372047937"
      },
      {
        "file": ".angular/cache/17.0.5/babel-webpack/61eee7986fa4c3d835273529f2e0623c3f2acbf629d4046e478f57ee443d61d8.json",
        "hash": "16206988409361550470"
      },
      {
        "file": ".angular/cache/17.0.5/babel-webpack/62131ef7e0d6fcaa84a5437ba05dfc6952dc940fea0075d8f5119c2a6b6ff8c1.json",
        "hash": "4120745059270132432"
      },
      {
        "file": ".angular/cache/17.0.5/babel-webpack/638808a5bfa35851ad589854ff2a112b7b31be3acb6694fe5d6503684635db68.json",
        "hash": "13058757251935344317"
      },
      {
        "file": ".angular/cache/17.0.5/babel-webpack/6459e0afe2ef443df09466a43718f9cda3125702ac71a12b0889772ccffb51d4.json",
        "hash": "17734245171524754328"
      },
      {
        "file": ".angular/cache/17.0.5/babel-webpack/6501d938312ad02193f1477d8a98f354b69b3a2f2ca2dbd1b05f318321d9d3d1.json",
        "hash": "7450718730602824001"
      },
      {
        "file": ".angular/cache/17.0.5/babel-webpack/6522fdf163754441cc72f80e493a1bdba9ca69f6065a700a4d15ddcb9edbd8d1.json",
        "hash": "8201059583793863877"
      },
      {
        "file": ".angular/cache/17.0.5/babel-webpack/6624223bfb9a7d365f088a2356cced0c0a74d2a4f1238241ecca15eaefe0e68e.json",
        "hash": "6360143397289792721"
      },
      {
        "file": ".angular/cache/17.0.5/babel-webpack/668598174bda19524a445fdefd94d6cfaa343a4dc50eddcc278321a611e893a7.json",
        "hash": "9942315239681089443"
      },
      {
        "file": ".angular/cache/17.0.5/babel-webpack/66bfa70ad6eca7ce9198b5e9df235c83ae2542728176134f834d7f8faba5d85e.json",
        "hash": "13706853998879806786"
      },
      {
        "file": ".angular/cache/17.0.5/babel-webpack/66cdf91dbf5370ece9aad6a5d08edf68fcad5137d85d0c1c537d8042e38ee616.json",
        "hash": "1059145768451183384"
      },
      {
        "file": ".angular/cache/17.0.5/babel-webpack/68c71e6c35764cc5bbe29e17292d0bd52b5554d7a769614cc9a6d4f46f22b55c.json",
        "hash": "1012467198348088998"
      },
      {
        "file": ".angular/cache/17.0.5/babel-webpack/68e86cd29024f1caeab9c052977ada8e48c37b18e4e71c1449415792d0857b3a.json",
        "hash": "16788640096927857443"
      },
      {
        "file": ".angular/cache/17.0.5/babel-webpack/697e0ee6646443bff2c0ccf4b25d35b2ba8f304c5e5c341b209b1240ca416178.json",
        "hash": "14731128106147684848"
      },
      {
        "file": ".angular/cache/17.0.5/babel-webpack/69da75c3e25869bcc91cfb1fb4314febfd9e79848982651ef482a2bfda8181b1.json",
        "hash": "15079715467847767171"
      },
      {
        "file": ".angular/cache/17.0.5/babel-webpack/6a460ed56d2c4ffdb2938fb1747fc4caefbeb8c117e7cb8f4d71494a0aa67719.json",
        "hash": "16769541000088331102"
      },
      {
        "file": ".angular/cache/17.0.5/babel-webpack/6b580084d440ac7d5db708caa3c49cc57aab663e054804cd0a78c505f18be724.json",
        "hash": "9451941141033685168"
      },
      {
        "file": ".angular/cache/17.0.5/babel-webpack/6bd9c657fd31af9e7ff4cbfcef83af9d2250cda47c3473250ed76f648e91a8ac.json",
        "hash": "13323935617288027192"
      },
      {
        "file": ".angular/cache/17.0.5/babel-webpack/6c157d2bcda524760a2f508f6a725553f13f54b26860369e1ec186a85fb7247d.json",
        "hash": "76053185818302666"
      },
      {
        "file": ".angular/cache/17.0.5/babel-webpack/6d4ebb2584ba344178928cb0e98ece908360d6f1f54fd94e63fdd41c39898780.json",
        "hash": "8144033687968740370"
      },
      {
        "file": ".angular/cache/17.0.5/babel-webpack/6d68a9dbde39c4bc2abc681444715617640cfeedad62f703aea512e6a9149db9.json",
        "hash": "7958064402567093841"
      },
      {
        "file": ".angular/cache/17.0.5/babel-webpack/6d8637b00ebe17a31f90798c6795b5a4eba082d83b6990d64301488824a63df2.json",
        "hash": "6354430718348977705"
      },
      {
        "file": ".angular/cache/17.0.5/babel-webpack/6db33a02b6f7ca89013e6297e8734b765a4c41c0f267eda70f886ce7233ae88a.json",
        "hash": "10785896480785233072"
      },
      {
        "file": ".angular/cache/17.0.5/babel-webpack/6e11d6082b19cbacf431887ef1a30900055cc752546212e726add728a9cbe078.json",
        "hash": "11720429515823462784"
      },
      {
        "file": ".angular/cache/17.0.5/babel-webpack/6e8daea0e4061a574d8c74c6447fb596e7c18aabca6773a34d084b421ac1ee8a.json",
        "hash": "3007195091496822558"
      },
      {
        "file": ".angular/cache/17.0.5/babel-webpack/6e94cd05b9a7601436a4c65e2187a954c2797fdf4e654fba181bf9482fd1769d.json",
        "hash": "739465895003613605"
      },
      {
        "file": ".angular/cache/17.0.5/babel-webpack/6ee818536132b42d405cc457854cc539082b2ba0f6fd4f6face9b781eca158bd.json",
        "hash": "5494136682217382191"
      },
      {
        "file": ".angular/cache/17.0.5/babel-webpack/7221fb227430a73a65d3088a6e7a101fc1617e74a98569021af28d2c41508085.json",
        "hash": "4427316260412474400"
      },
      {
        "file": ".angular/cache/17.0.5/babel-webpack/72ae7e1dcf8bda56030964905d3950776ea6b2e2e9dd7dff3e994533109e5198.json",
        "hash": "9498394191402604941"
      },
      {
        "file": ".angular/cache/17.0.5/babel-webpack/746a6952b8ef0409427e24b0eced5bf2cd0f5061b590cbbc56cafac4de46071a.json",
        "hash": "3228539436188351710"
      },
      {
        "file": ".angular/cache/17.0.5/babel-webpack/74b67a3303bc9a7eca411bb57f5f79911bb3d7c3b8371382c8dee835b0c893bb.json",
        "hash": "15338975093088756897"
      },
      {
        "file": ".angular/cache/17.0.5/babel-webpack/75d84277562a14eb9249f6c50870ff93cbe6af77b32412312213fc1e7dc0621c.json",
        "hash": "1006749118331575081"
      },
      {
        "file": ".angular/cache/17.0.5/babel-webpack/75fc5d88f343701a1f26946ff7cbd4b2549f670988a0783b46074fd6b9a13d06.json",
        "hash": "16733490276309678287"
      },
      {
        "file": ".angular/cache/17.0.5/babel-webpack/764b6f644a1ebbf6bd509f28c350ca8ff98b0ca412ba003fa735ee5dce2ea981.json",
        "hash": "16927012307755334123"
      },
      {
        "file": ".angular/cache/17.0.5/babel-webpack/767dab744d5d1c6ccd8668a2819c33d87b003facdbd329ecdf9e20d20fa14182.json",
        "hash": "14188450877098533435"
      },
      {
        "file": ".angular/cache/17.0.5/babel-webpack/769f5017f589e3a75a9f6c796fa21c8014f2e6bb40932990354b2f0908c14ba9.json",
        "hash": "10056920990475536555"
      },
      {
        "file": ".angular/cache/17.0.5/babel-webpack/76cc72cd92244f658ffcafc9fbdb99ae6df366135695ed72621cccc92c3add86.json",
        "hash": "11989108558433088154"
      },
      {
        "file": ".angular/cache/17.0.5/babel-webpack/775a67c935a079c40d6c9be3b0656a9469e9891ababd13a437881895940f9d8e.json",
        "hash": "6842320534210341382"
      },
      {
        "file": ".angular/cache/17.0.5/babel-webpack/789183992de570bca731258242b994415eb7c69db4bbd096c4faa46154d3474d.json",
        "hash": "1993003601149972151"
      },
      {
        "file": ".angular/cache/17.0.5/babel-webpack/78a35a02c7766d3b85383ace203b5a7c7341ffa4459cbce1609fca6c2293f527.json",
        "hash": "4303414846914071413"
      },
      {
        "file": ".angular/cache/17.0.5/babel-webpack/7907d2acb04800d16bfdc7d65c8c473dbfb0538289ecd4db6e46ad5872db2abd.json",
        "hash": "15518290319976189098"
      },
      {
        "file": ".angular/cache/17.0.5/babel-webpack/79b4b98a94fa8e12c0e14918958b8bbe9f581d0bc2273041f038031dc3b3ce9f.json",
        "hash": "18206209308705323731"
      },
      {
        "file": ".angular/cache/17.0.5/babel-webpack/79f0dccdc6e2fffac80ac2f0ce44a21ab1db9f95b0376a22073bdc00df97d8a2.json",
        "hash": "2423392216199709243"
      },
      {
        "file": ".angular/cache/17.0.5/babel-webpack/7a75c47521f23c839fd086fa79b2b866ac46ec6e2d198b7413e3b0e1b7b320b1.json",
        "hash": "5630808908192022183"
      },
      {
        "file": ".angular/cache/17.0.5/babel-webpack/7a8af06330e45d5b119360fdbe23de02a4384b740b035d12d2cca3026dd82ed5.json",
        "hash": "17600553899317526271"
      },
      {
        "file": ".angular/cache/17.0.5/babel-webpack/7b87c968dac86f014deada884e4e74dfa3eb5b9d930bfd4da42a8c102a1d674d.json",
        "hash": "15829067019420606937"
      },
      {
        "file": ".angular/cache/17.0.5/babel-webpack/7c373eeaff8039653962dc053730ce1ae8c8d1daa3bda04dab76967ebdecf4ce.json",
        "hash": "12975112552654694891"
      },
      {
        "file": ".angular/cache/17.0.5/babel-webpack/7cc334523692a1dd8b6294ca71a3e93b349a469fe04a1c42fc258a2a7699ce51.json",
        "hash": "2574646419476771772"
      },
      {
        "file": ".angular/cache/17.0.5/babel-webpack/7da68e79c320b0c5102c17870bcb7a46edb5097f50dca3b814648be38409da58.json",
        "hash": "12738699189197347710"
      },
      {
        "file": ".angular/cache/17.0.5/babel-webpack/7da905954a7e85e73fc870adeb64f4584c49ef12c445a051a16d3d7f9f7ce2ce.json",
        "hash": "13979633700221187083"
      },
      {
        "file": ".angular/cache/17.0.5/babel-webpack/7dace259183edf590eb7d83d9b61df23065b167930dfb7c6743c21df060039d7.json",
        "hash": "11335355482775951132"
      },
      {
        "file": ".angular/cache/17.0.5/babel-webpack/7db69ff8424919c77607cd5406dccddd29ccdd241c2fb1d109aa52b045c72e41.json",
        "hash": "5727620336256766871"
      },
      {
        "file": ".angular/cache/17.0.5/babel-webpack/7dfc6de82a6b468638f3986c8059faf01a6463c0a6c47eb4f08d5d2e18738986.json",
        "hash": "5826576576319228328"
      },
      {
        "file": ".angular/cache/17.0.5/babel-webpack/7ee158d21888f57550a55dff6ff84853b32d884be7e520d8f7ee2faa6e97b356.json",
        "hash": "14163260404183581161"
      },
      {
        "file": ".angular/cache/17.0.5/babel-webpack/7f80c88ced05c90ad64d77ddef4c0646c2b569f40ae815bb527b79f2b7304b3c.json",
        "hash": "11959775700762791751"
      },
      {
        "file": ".angular/cache/17.0.5/babel-webpack/8014e0bbfb167003e2b0482a34afbf11683d347f815401ed0f341ef116d6abf4.json",
        "hash": "16129360713596876161"
      },
      {
        "file": ".angular/cache/17.0.5/babel-webpack/8058d0f8e11ea66291b1e225565f12e7c0363d0df4cd8168a0dc119e50953b13.json",
        "hash": "8081923184663310212"
      },
      {
        "file": ".angular/cache/17.0.5/babel-webpack/80bbf933e262967d511e7ed0f6f8efe03478452e9161a8ab8ebfc3d9242a4eec.json",
        "hash": "10950560787995552169"
      },
      {
        "file": ".angular/cache/17.0.5/babel-webpack/80ccba5394c24c47629535f16333a16cc229da93129ae1e0bceb7ce7c7b3b80d.json",
        "hash": "14030211695204761692"
      },
      {
        "file": ".angular/cache/17.0.5/babel-webpack/81a93283f80837dc6dc8ce9b238feca36a9f69f3a3c9fd1d150604669c7bd101.json",
        "hash": "16532420507573909183"
      },
      {
        "file": ".angular/cache/17.0.5/babel-webpack/81b07c262d6b389ad1b51798e48efb2b02335f1a8f0b65eb24dfc5feda657046.json",
        "hash": "9597339635559177625"
      },
      {
        "file": ".angular/cache/17.0.5/babel-webpack/81d876b89c5ec815c19eea996b2dd827327927ac2b2bd11ff330a21b4ec7087e.json",
        "hash": "17368817022599438110"
      },
      {
        "file": ".angular/cache/17.0.5/babel-webpack/826f01b4d7d704f2b96efb1082ba0f54813f508d3925c58581adc1046740abd3.json",
        "hash": "8906868896038845011"
      },
      {
        "file": ".angular/cache/17.0.5/babel-webpack/8297e8d41f494932342b769a347cffe41df79caf9bced75b07daba9ec1fefe88.json",
        "hash": "15498232070528930632"
      },
      {
        "file": ".angular/cache/17.0.5/babel-webpack/82ec5820a2818b6725b3627137d5e14b5cae705a74620a951ad3b37bac257da5.json",
        "hash": "9212847158813547594"
      },
      {
        "file": ".angular/cache/17.0.5/babel-webpack/836497126cb6b24883a4f5bfa47467fe3ed045837b94d5ba170cfea010c7259d.json",
        "hash": "9933929736721846607"
      },
      {
        "file": ".angular/cache/17.0.5/babel-webpack/837f77ea5c0eae5e4605525de9d1b8ecdc1599cefa0132ea67815407b10b4b80.json",
        "hash": "15932832151275594636"
      },
      {
        "file": ".angular/cache/17.0.5/babel-webpack/84e5a996e15573384b899a7fe5bc806efb36b84ef4ebbf5e68059cc8c981f767.json",
        "hash": "9786871429945586017"
      },
      {
        "file": ".angular/cache/17.0.5/babel-webpack/86a4015d9800ff4fcfa5ac550f6abd86677051e6ca5cb1d0308fa4577bbac769.json",
        "hash": "8377693834315305868"
      },
      {
        "file": ".angular/cache/17.0.5/babel-webpack/88101754a59bbb198f419ef8428b4d500f4b1fd00c3569f59a9a5a6b9946b4a4.json",
        "hash": "7837866492553468270"
      },
      {
        "file": ".angular/cache/17.0.5/babel-webpack/897a22bca7cb07091f1e43018fe131206eeac7c45365f8bdb5ad03751e0ddf1b.json",
        "hash": "10157369227349389289"
      },
      {
        "file": ".angular/cache/17.0.5/babel-webpack/8a7c58525c81ca1f997dc637b570b99c856783b1ad264e8edfff341e91f61c56.json",
        "hash": "16510360266829308233"
      },
      {
        "file": ".angular/cache/17.0.5/babel-webpack/8acdceed4b4d3aa3c81f176ca0c825a4d85141c1d2a1d81acc8fe148ef6ba1a6.json",
        "hash": "13536107623206329004"
      },
      {
        "file": ".angular/cache/17.0.5/babel-webpack/8bc6be47b690268307ade6491b258e32a9578bb6c37c6f37dd57b4b4df5faaec.json",
        "hash": "9523786850383641682"
      },
      {
        "file": ".angular/cache/17.0.5/babel-webpack/8bdbca542531fc93465453fb1ee9efb29dec2cf914e670a348b4b673f9f9f84c.json",
        "hash": "8660329210970568646"
      },
      {
        "file": ".angular/cache/17.0.5/babel-webpack/8cc82d5ddd9dfd5dea68fb7a09b33e31615740c613e743a26942c271e90f6c6b.json",
        "hash": "1964308261736270104"
      },
      {
        "file": ".angular/cache/17.0.5/babel-webpack/8ccd2216c2b1730e6e00396cd106a5fa46ea42ca01af55a5b68bb8e13bac2c6a.json",
        "hash": "14414075134207907758"
      },
      {
        "file": ".angular/cache/17.0.5/babel-webpack/8cd6a681d1dea6415287b9e58fdd9c95a0bea5e6dc9fb4bf18fe62903189a6c9.json",
        "hash": "2537708187361086365"
      },
      {
        "file": ".angular/cache/17.0.5/babel-webpack/8d009d46001821a7b39d240aaecc135e2571ad281fcaf495a3f6012db3f9174d.json",
        "hash": "10343332305380355967"
      },
      {
        "file": ".angular/cache/17.0.5/babel-webpack/8ddd796e5829b8812268e10a9741198fe21866b36f26d6777c6f8c0c5779ac34.json",
        "hash": "1212913966978209918"
      },
      {
        "file": ".angular/cache/17.0.5/babel-webpack/8e793d91b07025197b39d7e7cb8be18d36724d8fe984aa6dd5c0f7ce0a9a172d.json",
        "hash": "8497043516093865584"
      },
      {
        "file": ".angular/cache/17.0.5/babel-webpack/8e808067eabbeb9be73932e9fdea3fbba0966fb80cc6e79ccc2b884739e39053.json",
        "hash": "8891030042286384263"
      },
      {
        "file": ".angular/cache/17.0.5/babel-webpack/8e8151c0ad5bebdae0adf5e409b62bd183b6d38882e5f3aac4dbbb1b84f5c955.json",
        "hash": "5118268504097642381"
      },
      {
        "file": ".angular/cache/17.0.5/babel-webpack/902f50f2734e7f720e55a9a1a1628e0c7243db4618b24b27d33ca3f16417eef2.json",
        "hash": "8042987558513741437"
      },
      {
        "file": ".angular/cache/17.0.5/babel-webpack/924f3e3557fbbb3e33563ee0717338065918bb42a761814d0ea790ec47a2c386.json",
        "hash": "8325429818890340180"
      },
      {
        "file": ".angular/cache/17.0.5/babel-webpack/93d8787372ce89c4986a739f050db8f253d0b24d910bada30d248a352d631f03.json",
        "hash": "9757123184019712875"
      },
      {
        "file": ".angular/cache/17.0.5/babel-webpack/940ee486e4ca53dcb0f53d3db46784cf0d17fd5ace80d405b6b850248b4b2baa.json",
        "hash": "16852085243875130012"
      },
      {
        "file": ".angular/cache/17.0.5/babel-webpack/956fdceeac3a222f52d3b0916eae05427ce4b2b9d3c1590af4c17efe0a8c3960.json",
        "hash": "10303235089289774480"
      },
      {
        "file": ".angular/cache/17.0.5/babel-webpack/969d9e2fa6bc74fef4a55bab708e5836a2f26732f6c4316909ef4e45f45862cc.json",
        "hash": "3157227384097537858"
      },
      {
        "file": ".angular/cache/17.0.5/babel-webpack/969da79a60f3290446a81cab94879e36c06231bbd2935f51326f73293e639c64.json",
        "hash": "685996991810845628"
      },
      {
        "file": ".angular/cache/17.0.5/babel-webpack/977eb846ec1f356c3c5ce764c665b3a228ba762404f672bc08a26985f939a23f.json",
        "hash": "4708710421849219735"
      },
      {
        "file": ".angular/cache/17.0.5/babel-webpack/98695e1157b24ab1778c2279c8485b57cedc1c1150f29a32a53ec090dcc6aa79.json",
        "hash": "6923125350324049877"
      },
      {
        "file": ".angular/cache/17.0.5/babel-webpack/98dca9d54ce0f4250b66de2b3698baf3f8c3897bb148a92cbe2a781ae3795520.json",
        "hash": "14910356753066203855"
      },
      {
        "file": ".angular/cache/17.0.5/babel-webpack/99072ff526a55224cc444e783152b00bd980744f057986c9a48d3b60c17c796f.json",
        "hash": "15439124262492700085"
      },
      {
        "file": ".angular/cache/17.0.5/babel-webpack/99cd130cc81ef352f3a23d28bb53b0801133bdb88fe11c39a36f39322674229c.json",
        "hash": "8592483183837134191"
      },
      {
        "file": ".angular/cache/17.0.5/babel-webpack/9a23907c81d33da46234eed166cad21369d3b56b00c87f4056c5e51597917ed1.json",
        "hash": "17875823731159884024"
      },
      {
        "file": ".angular/cache/17.0.5/babel-webpack/9a3e12d06f7aa919a21b9eefe598de2ca3ba112c5b57add91bf3406beb255f00.json",
        "hash": "766655877334953987"
      },
      {
        "file": ".angular/cache/17.0.5/babel-webpack/9ae5604973bfd61fa68507d44da6719a4800fe2e2ef0ee705b9bc2b25996eea0.json",
        "hash": "4494430656367175777"
      },
      {
        "file": ".angular/cache/17.0.5/babel-webpack/9b3cd752b94605c61dd3b63df81904add3eb635f7a20f7e85e9ae5a2b6a32c02.json",
        "hash": "2763727462214998714"
      },
      {
        "file": ".angular/cache/17.0.5/babel-webpack/9cca4341a6c9f24794b4b14263d1289849608881d97135adb5716a458cad8684.json",
        "hash": "5147075381761390873"
      },
      {
        "file": ".angular/cache/17.0.5/babel-webpack/9ced7fb81406ca0b51a02ba9326d4de312554b0c267ae5c7fddd0f7d6972b14a.json",
        "hash": "14337638741252624721"
      },
      {
        "file": ".angular/cache/17.0.5/babel-webpack/9d124ef5f2564eb035805f34fbc44932b1f03a91acca1b49129dba8a952e4973.json",
        "hash": "8130900128312972694"
      },
      {
        "file": ".angular/cache/17.0.5/babel-webpack/9d3fad40cdac2fa043f8e02f8e8c62798a586f0e6b21152c0a0eb35bfd44f8d7.json",
        "hash": "5374078970992253078"
      },
      {
        "file": ".angular/cache/17.0.5/babel-webpack/9d6f971ade12e3fc5cd776ee6514901e91e7f53fc4652a536c206160d132a65c.json",
        "hash": "5887158121292225761"
      },
      {
        "file": ".angular/cache/17.0.5/babel-webpack/9db157630908e50947cf65784a88805c6dddf818e8645fc9ee8d4ec2626b4f7d.json",
        "hash": "5575713308152866239"
      },
      {
        "file": ".angular/cache/17.0.5/babel-webpack/9e284f0abbef7c3287cc4fdbfcbb01639b733a87b2d0fcf796fc1ec9a7a1869a.json",
        "hash": "13852209510557452138"
      },
      {
        "file": ".angular/cache/17.0.5/babel-webpack/a02612924e61f9852d3c6914f9cab31972e188e2137aecf0f5c84c19f4da27c7.json",
        "hash": "8019043812649702194"
      },
      {
        "file": ".angular/cache/17.0.5/babel-webpack/a0ab94d2f681da1412be266cdd828970baae706d7fd6127367eafdb3640dd341.json",
        "hash": "1861041410248672176"
      },
      {
        "file": ".angular/cache/17.0.5/babel-webpack/a27dddd2216c96c25f5e4698463c693ffc557dec722e0031135f34f409d95a63.json",
        "hash": "14629610400693259423"
      },
      {
        "file": ".angular/cache/17.0.5/babel-webpack/a3030af1e6cd5452fd88c08a50bfe1a08838e1a127484653bebc7d367fc64494.json",
        "hash": "9276653153797846569"
      },
      {
        "file": ".angular/cache/17.0.5/babel-webpack/a3712ad03c500e49cc6414fd9dec868430b8640dcbdbaf538fdbf05b783b93fa.json",
        "hash": "6737638694614124171"
      },
      {
        "file": ".angular/cache/17.0.5/babel-webpack/a64b780d85e36052324444fa0075cbf842f5a0f82336e1c9390bed4a105148af.json",
        "hash": "3612581080194066460"
      },
      {
        "file": ".angular/cache/17.0.5/babel-webpack/a65486d2fec0117f8a089714a18405c4941b33f27b625adb7d0858fecf3137cf.json",
        "hash": "9060076690368700838"
      },
      {
        "file": ".angular/cache/17.0.5/babel-webpack/a65aecb7a1e0694882d617af61b36b60a9bd78607b411d8ee43d9b917dc3bd52.json",
        "hash": "916127761269749601"
      },
      {
        "file": ".angular/cache/17.0.5/babel-webpack/a72a7843784bd0b8197ab1b4661003489982599bd6c8a11e9b043b4c1f537bd9.json",
        "hash": "2875987743956100936"
      },
      {
        "file": ".angular/cache/17.0.5/babel-webpack/a8593be286c05f274da75ab904cd4574659b65d1dac8b5b2c9bbbc68ea4ea777.json",
        "hash": "1492546232109252583"
      },
      {
        "file": ".angular/cache/17.0.5/babel-webpack/a968db1bb07c1456ade02c3f6b9d51116766acf13f99188c13617045fac9762e.json",
        "hash": "9716959995337864174"
      },
      {
        "file": ".angular/cache/17.0.5/babel-webpack/aa0700b849fa15f97ab670215b8e2d638eaab52a5351e098b9ad5138b308f74e.json",
        "hash": "16281279319357776190"
      },
      {
        "file": ".angular/cache/17.0.5/babel-webpack/aa1a8ccae402a4c668b356c2fe8e4375fe700dbbbaa90adfac8c810d84dd48f5.json",
        "hash": "1125730116637339337"
      },
      {
        "file": ".angular/cache/17.0.5/babel-webpack/abd47f394e3bf664377f63e15f50a21d2fedc042f9240bfe67bdc7490002e383.json",
        "hash": "11679143202696477259"
      },
      {
        "file": ".angular/cache/17.0.5/babel-webpack/ac60f1138a6d2cc7d60fd9e6a830ab061035dcf6982052295cc0a1d8f4f29963.json",
        "hash": "1709514677130651931"
      },
      {
        "file": ".angular/cache/17.0.5/babel-webpack/ac97cb6f3c5f1763d98dbb26386b6caf428c3d8200f084ec9b9db085e3a3accf.json",
        "hash": "11855385404028344313"
      },
      {
        "file": ".angular/cache/17.0.5/babel-webpack/aca4fa8662979d4fe6fdd6d209e953c3e11590ea16b3d9207a1c718283465f36.json",
        "hash": "16320786485352841119"
      },
      {
        "file": ".angular/cache/17.0.5/babel-webpack/acd1177a3eb0af6401eda4e918d902466f461c843193123b47b02ea8dc663126.json",
        "hash": "3655471121198941975"
      },
      {
        "file": ".angular/cache/17.0.5/babel-webpack/af179d1687a9fcbf471cdc28d4d75c84a7ffce99d1606ea3cc230ff758630d09.json",
        "hash": "14910063724146095466"
      },
      {
        "file": ".angular/cache/17.0.5/babel-webpack/aff9ddaa46ae67038e0af422e1c30521c1928745a2f05f8c9b36a2f7d207ce3f.json",
        "hash": "1023113707350208497"
      },
      {
        "file": ".angular/cache/17.0.5/babel-webpack/b0ea5ee1ce651429eefbe59b2d248f57f4b5e764e5bbbaf68f628311776c6f37.json",
        "hash": "12598831147036973254"
      },
      {
        "file": ".angular/cache/17.0.5/babel-webpack/b20593e046a898d1e7d85591397c71a92eb0040ba85175f2af20014b5aeef2c1.json",
        "hash": "2991640962046868192"
      },
      {
        "file": ".angular/cache/17.0.5/babel-webpack/b234ba8ada1e6449df16dbbbf3bbbfed820d9a09edbf51a064ddfe8c9de759c7.json",
        "hash": "7628184588993703547"
      },
      {
        "file": ".angular/cache/17.0.5/babel-webpack/b2d52d25fbab672ffe3dcf9f56086cff5e3f2bb0bde82f6dbbf57b70162958b9.json",
        "hash": "14707886870019208915"
      },
      {
        "file": ".angular/cache/17.0.5/babel-webpack/b30d1a300da0b3d3b8bcdedc32d79f584cae060456b8d4a97a12fb7cda89b7c3.json",
        "hash": "3164937738542791407"
      },
      {
        "file": ".angular/cache/17.0.5/babel-webpack/b398578b19aa84c3314c03dcd3a96b3b9bd6fc793e229c565191317fb12737a1.json",
        "hash": "4357418779189354337"
      },
      {
        "file": ".angular/cache/17.0.5/babel-webpack/b506122a629960fd25274cdb823e1a993aa733925399072f3a92bc5ed85e8905.json",
        "hash": "11044467187481921823"
      },
      {
        "file": ".angular/cache/17.0.5/babel-webpack/b5e1d1ab11fe0987e740648f50b125849d85be8176c8ea9d6d33dcfd44bc412d.json",
        "hash": "7491263764726019230"
      },
      {
        "file": ".angular/cache/17.0.5/babel-webpack/b698e29fc148db97baccf5d11b12b23e52e96a935eaaf23e9c7fe73cbf8d1ea0.json",
        "hash": "8782775916905056719"
      },
      {
        "file": ".angular/cache/17.0.5/babel-webpack/b6e4ee680911cd02cf34538b367ba956ce391146ca5f7bd75b8405c174636ecc.json",
        "hash": "17190618928375888551"
      },
      {
        "file": ".angular/cache/17.0.5/babel-webpack/b6e86efff37c5ebd076104f19186a53d1def31ee6fac5f7a5934012383b4520c.json",
        "hash": "1905602878609074763"
      },
      {
        "file": ".angular/cache/17.0.5/babel-webpack/b722443fb39d1287239c305184d4d49d8c3abcf703a069211eeb4783fb7ad05e.json",
        "hash": "17669653202741747878"
      },
      {
        "file": ".angular/cache/17.0.5/babel-webpack/b822d7565650a43e618cab87040bf66f3197eeffe3b426e2864cc929d33dab31.json",
        "hash": "4619982971168745919"
      },
      {
        "file": ".angular/cache/17.0.5/babel-webpack/b8b416fd71e19db7c030718e826ea6a104e112e015133ea57aa8ea43d11cf685.json",
        "hash": "11959567817509899051"
      },
      {
        "file": ".angular/cache/17.0.5/babel-webpack/b8f8798dd26072d20d9a0c83f8bfb3c64c8393edfe64bd93cb79a60350cf9af3.json",
        "hash": "287483737040723945"
      },
      {
        "file": ".angular/cache/17.0.5/babel-webpack/b91774d12e064bda92be4d804da5234375736a47bed808eee4103cc64bfb9a8c.json",
        "hash": "7844744895309996312"
      },
      {
        "file": ".angular/cache/17.0.5/babel-webpack/b9bab6bba8ca36aeb0b37b116523b2243b527b1d84e8aaa3735dfc38993451f7.json",
        "hash": "2289252090096192829"
      },
      {
        "file": ".angular/cache/17.0.5/babel-webpack/b9f11567c19b19b9511537ccb295da150d159eaf36a908f70f731c693d802538.json",
        "hash": "16706375766605890365"
      },
      {
        "file": ".angular/cache/17.0.5/babel-webpack/b9fd73ec79e8f9d1ea3b0a34d7cd71428f01c285fa6facd80d2504f87adcb1e4.json",
        "hash": "6831025650076701079"
      },
      {
        "file": ".angular/cache/17.0.5/babel-webpack/bb652efd930e335fe6c88e3cd3a406eaea38e0f68c3346501a6b51d8e81ef9a2.json",
        "hash": "9808533357633553715"
      },
      {
        "file": ".angular/cache/17.0.5/babel-webpack/bd25ef4a614df02df209038ea0fbed6834a6962d11bc8c7dd2da51bfb23d251e.json",
        "hash": "408750174979149984"
      },
      {
        "file": ".angular/cache/17.0.5/babel-webpack/bd5c1709a99b42c81b9f06e0208b0dd356748c31b058a4d742428133e3512f1f.json",
        "hash": "11471022507789394014"
      },
      {
        "file": ".angular/cache/17.0.5/babel-webpack/bd5d22bc1f450db3d0c8b05d318751268efcb85c84a1f65657c2c7dfc7074868.json",
        "hash": "8184676217497290549"
      },
      {
        "file": ".angular/cache/17.0.5/babel-webpack/bea36fb78666809e123f894f1397ea8934448ad5d6b1ab774a9201a0b1301d17.json",
        "hash": "15906340217902412488"
      },
      {
        "file": ".angular/cache/17.0.5/babel-webpack/bec08ced61de05736b6525a32481f5bb1a9c2b1521f1011604fc9b562c83a6f5.json",
        "hash": "13552433563636251756"
      },
      {
        "file": ".angular/cache/17.0.5/babel-webpack/bee78e8fd95d623a0b52b8955adad925e5ceacd3f89586c60670a7085f345af0.json",
        "hash": "12392487331212307039"
      },
      {
        "file": ".angular/cache/17.0.5/babel-webpack/bfb59864b030186e7d1691f126f154fb79a903ffdd8511c609744b33204b5a86.json",
        "hash": "12414991720872888085"
      },
      {
        "file": ".angular/cache/17.0.5/babel-webpack/bfd6e529803c2476e8f14de8001eb38cba68568d4a988f92bf122b28bc0ae8a5.json",
        "hash": "5448456204713653647"
      },
      {
        "file": ".angular/cache/17.0.5/babel-webpack/c05865629bec5af300a910d134cb97db1baa1f559f75026d763bdcfebde9477b.json",
        "hash": "820308048045102499"
      },
      {
        "file": ".angular/cache/17.0.5/babel-webpack/c25d4f8d4f3eb34f7dcf7ce786785c7ee759cc66efcb54b62a5094b09ff17ea6.json",
        "hash": "10896723042635877666"
      },
      {
        "file": ".angular/cache/17.0.5/babel-webpack/c36277eeb906895f58e74bb017b7e250dfa73e5639a437d34d50d1176838c4e6.json",
        "hash": "13137536664664118086"
      },
      {
        "file": ".angular/cache/17.0.5/babel-webpack/c36342e26b93a4e2870682571df47ac11be062e51d1aaf0b3ed165ac85cca126.json",
        "hash": "1851475904032977544"
      },
      {
        "file": ".angular/cache/17.0.5/babel-webpack/c59879cffd289379c0b629f0f862c0e6a9e28dbf1fdcb346abd62d76075ebdd3.json",
        "hash": "2815630910862764975"
      },
      {
        "file": ".angular/cache/17.0.5/babel-webpack/c5a696a5096e4301b4ebcf38d776bc392aacc6ea1d32f2d806fd64536146b98e.json",
        "hash": "17096384757476900367"
      },
      {
        "file": ".angular/cache/17.0.5/babel-webpack/c618fc864af7166388314ff6c555ca35f2c444dc0951f7265171b5158d014aaf.json",
        "hash": "10981960756905383930"
      },
      {
        "file": ".angular/cache/17.0.5/babel-webpack/c63ad834137072b4b503773dba26171df2681640c581416c7a34d77bc2c46a6f.json",
        "hash": "11100303388966038649"
      },
      {
        "file": ".angular/cache/17.0.5/babel-webpack/c79b92c266db8968cf4a6725302dc810734749876c19de527aea7d65d68fc5c9.json",
        "hash": "8316287182172960454"
      },
      {
        "file": ".angular/cache/17.0.5/babel-webpack/c7c8773506932d263cbce0c4af11774cb7ec6829bcd16da4e129b45e49a3da9b.json",
        "hash": "10485035806527808388"
      },
      {
        "file": ".angular/cache/17.0.5/babel-webpack/c8639ada8679ce03e312c06b7019e39fb8e375551158efe620eb41ac63bf08e8.json",
        "hash": "8459984959596165631"
      },
      {
        "file": ".angular/cache/17.0.5/babel-webpack/c9299be26555c3d3cf8f6d0162fe298ec0353563b8119e2611ed46b1bb9d85c9.json",
        "hash": "12953149610883938028"
      },
      {
        "file": ".angular/cache/17.0.5/babel-webpack/c92dd0994ed2149cca024536b62258083eb9917fa955f0cfc168674989205b09.json",
        "hash": "8165764015481205895"
      },
      {
        "file": ".angular/cache/17.0.5/babel-webpack/c97676145f6b4cdc8455426acc3e0e1ed197b6b761d8e41744e049a6cad2dbfe.json",
        "hash": "2787489694466943020"
      },
      {
        "file": ".angular/cache/17.0.5/babel-webpack/c9e8b099b743c914e8139c44f9d6f2e1d31d82fb61ec1c5d35f424f6f1960092.json",
        "hash": "2793335780560979381"
      },
      {
        "file": ".angular/cache/17.0.5/babel-webpack/ca8fbc86e3e771c1ed151f3db8304815964681280450f3ad27f1abd92ad09bad.json",
        "hash": "3286456165753643506"
      },
      {
        "file": ".angular/cache/17.0.5/babel-webpack/cb0bac9b364f1582301d859745b2d0018cabc00cb55bb71ae850a82e44184324.json",
        "hash": "3748658423758058192"
      },
      {
        "file": ".angular/cache/17.0.5/babel-webpack/cbd2230e2bf935a075079eeab08575f8026799d0bd7ca6e766413a949a44aa15.json",
        "hash": "3640787454916340802"
      },
      {
        "file": ".angular/cache/17.0.5/babel-webpack/cbec2884b43aaec5bb3bdc46a117d4e32fe5b8063b92f3d193c61bbe991651ec.json",
        "hash": "6665600598013084912"
      },
      {
        "file": ".angular/cache/17.0.5/babel-webpack/cca689ac51f5be54f2a1c8d33414234f528ba958efd9921e55c9b4f463702ab6.json",
        "hash": "5591580271106333835"
      },
      {
        "file": ".angular/cache/17.0.5/babel-webpack/cd31ab3158885df51d0e54cfc5fe5634b2cb24062f305a0b7ad1762f5f0128cb.json",
        "hash": "7387560163160258561"
      },
      {
        "file": ".angular/cache/17.0.5/babel-webpack/cd83fe8bb583c5c5aeabd0218e5743eb44cd350b3fdbd68a4d630b4ac6b704e1.json",
        "hash": "3932428886141550252"
      },
      {
        "file": ".angular/cache/17.0.5/babel-webpack/cd9424d5fe8d8547c94215e9e3b20cb6cda3e72ff5776564a1357aa4c8bccda9.json",
        "hash": "2767457712388600124"
      },
      {
        "file": ".angular/cache/17.0.5/babel-webpack/cdff28f6251dc7b5609b401a7c97ca4ca69c29ad6b519810cd7ace3db682558a.json",
        "hash": "4626891165735861644"
      },
      {
        "file": ".angular/cache/17.0.5/babel-webpack/ce068c031de37e6b3254c3b522ed9e39c8938210140724fa5e6bc6a1ae9f1aeb.json",
        "hash": "429059117229003400"
      },
      {
        "file": ".angular/cache/17.0.5/babel-webpack/cf171b277e5222f74dce9832763b8c75efa7605f6e3cdfd078e1fa7243d5419e.json",
        "hash": "2537555791553114410"
      },
      {
        "file": ".angular/cache/17.0.5/babel-webpack/cf25848a3590a521f9e444a0b1c9dd1e7a0d3e519dea1c5130c84e3bd00bdf05.json",
        "hash": "293469176730720850"
      },
      {
        "file": ".angular/cache/17.0.5/babel-webpack/cfa506e796c9807f0a677f2d26dc18309f0f75efc7985a70a74cb5fc41f30464.json",
        "hash": "5866865963214384897"
      },
      {
        "file": ".angular/cache/17.0.5/babel-webpack/d0a8218bac4a92b8dd524fd8f19577dbda50113af3c9bff646af6f464552722c.json",
        "hash": "17258048012321471900"
      },
      {
        "file": ".angular/cache/17.0.5/babel-webpack/d172b278ecaef35d8438fd40b21dd49574ca4264d85212847c3daa7c3eb494e1.json",
        "hash": "5460046487897190309"
      },
      {
        "file": ".angular/cache/17.0.5/babel-webpack/d291bc9a9f36b2be4fc268ec8a362c3a38236518e3fd747a9c281c7e68fe3dd7.json",
        "hash": "3768256914040190866"
      },
      {
        "file": ".angular/cache/17.0.5/babel-webpack/d2c3029325bae874c3a785a4d8cddddead323e3094ccd4c9cb894456c9c35848.json",
        "hash": "16883076455501699017"
      },
      {
        "file": ".angular/cache/17.0.5/babel-webpack/d4ba038d316c935f0a4f021c7458cd8c31562c8be0675dee4fa400a2952507cb.json",
        "hash": "5492858410232219191"
      },
      {
        "file": ".angular/cache/17.0.5/babel-webpack/d4cbd70813f9657ec41d8d257fd6aab5e10ff14e08e14377d16fd54749131941.json",
        "hash": "440537973481242833"
      },
      {
        "file": ".angular/cache/17.0.5/babel-webpack/d51490620626cf5b18aab08e9530a359af84bae2a2c4802c85b29635f39fa00f.json",
        "hash": "5308250458442433760"
      },
      {
        "file": ".angular/cache/17.0.5/babel-webpack/d51b38cf30190540ccc968a93c4b174cb071f86c0a5ff2e427637b22aee27ef4.json",
        "hash": "7935376505064694175"
      },
      {
        "file": ".angular/cache/17.0.5/babel-webpack/d73492dbd0da79e51c229432bf768cf9ad2161b9ba950c0e7d2e4e9596cc59bb.json",
        "hash": "5491978351699064714"
      },
      {
        "file": ".angular/cache/17.0.5/babel-webpack/d74452f6e4f602a34ea4b00cce350dc9a0a29b1e25f5cbc8e348944b4c1cba10.json",
        "hash": "503912577389131424"
      },
      {
        "file": ".angular/cache/17.0.5/babel-webpack/d748da7bc527371f6877e060bbdb2276533818a84a04d4752c9ebc27140f4698.json",
        "hash": "16844196665371314712"
      },
      {
        "file": ".angular/cache/17.0.5/babel-webpack/d74cea655228cd691726083c719db2d320660cc270ea6e7f08c8f97b6b0415c6.json",
        "hash": "13005711533095429974"
      },
      {
        "file": ".angular/cache/17.0.5/babel-webpack/d75a3288837405360b48ef6847a1f37f751416ec5311a54da68ad858a992ec79.json",
        "hash": "17924141862615620667"
      },
      {
        "file": ".angular/cache/17.0.5/babel-webpack/d80c5dcdb8198df543bdca1240f39ac85920ef5b909498c57c7baeda112105d6.json",
        "hash": "17493285161397674398"
      },
      {
        "file": ".angular/cache/17.0.5/babel-webpack/d8e14b93d06986f92b19680f6b0cc87be9a434e71d246f869c85c96dc4a522d8.json",
        "hash": "9613453001047280024"
      },
      {
        "file": ".angular/cache/17.0.5/babel-webpack/d8fc52961aea7a88ad843e5db539a5268fc6ba7e0c6fe983d66f80782d15d7db.json",
        "hash": "8722795721977784824"
      },
      {
        "file": ".angular/cache/17.0.5/babel-webpack/da311fd68e9e75916cf283d65ab1e5af377d8e6a4484b069439ef4b0059d6dfe.json",
        "hash": "4996803745128814803"
      },
      {
        "file": ".angular/cache/17.0.5/babel-webpack/da77e6564c3bd138e83f7cb7ffb48c73cbcb7c97b5977d55501a861abf0e9f8d.json",
        "hash": "8761572180944533217"
      },
      {
        "file": ".angular/cache/17.0.5/babel-webpack/dae266914ff3bc6a6d224a83f564db792b6a82a3df331007e3c6909d19e40c89.json",
        "hash": "9505796605452723021"
      },
      {
        "file": ".angular/cache/17.0.5/babel-webpack/daf73ddfab51d84277ab02698516c013910971dd373e6d5bdd03eeafab6e6ae3.json",
        "hash": "11148139690676431099"
      },
      {
        "file": ".angular/cache/17.0.5/babel-webpack/db0091c4e79b84efcf99dc94f03c48085166145b4990d882b53fc974b2a2a9f6.json",
        "hash": "11013697374281614980"
      },
      {
        "file": ".angular/cache/17.0.5/babel-webpack/dbaaef86aa87dd00a2990d491a07d88fe7f0c6c86c382e61766144ce1b9efbe6.json",
        "hash": "8422479316797394227"
      },
      {
        "file": ".angular/cache/17.0.5/babel-webpack/dbf982254d224cc047bf57deaeaf4d0354f1a281458f0843a12cc15cd0f9f739.json",
        "hash": "15183517295420006138"
      },
      {
        "file": ".angular/cache/17.0.5/babel-webpack/dc0891fdf5a3cb0c922b5c4381efd226a8829756f5756c25f3d9232bced46113.json",
        "hash": "387380491725687928"
      },
      {
        "file": ".angular/cache/17.0.5/babel-webpack/dc8ceaa19f77f3a49b4515f2f1e6c3ecfe6e575f11f347d1467f8528de8ab4d9.json",
        "hash": "10288075620169155596"
      },
      {
        "file": ".angular/cache/17.0.5/babel-webpack/dd0f1acfd66c2403285a345b838e080764a50fd3c0b2b7b36884d1c6d4368080.json",
        "hash": "6708392564827924364"
      },
      {
        "file": ".angular/cache/17.0.5/babel-webpack/dd18882087b21ef99e32ef573e188bb0c9f7cb83f93c9451bac8b650d7fb0724.json",
        "hash": "7981445597802115614"
      },
      {
        "file": ".angular/cache/17.0.5/babel-webpack/ddec7d236a0bcdd350eec6d1f2c19047152cd6c2ff20f200fa93fecba07b6e95.json",
        "hash": "2374176889065065466"
      },
      {
        "file": ".angular/cache/17.0.5/babel-webpack/dee4faa6058efaacd90b1d1a3580c3e769c4c340db19b11ce22354f48d5f9755.json",
        "hash": "4619605314749480246"
      },
      {
        "file": ".angular/cache/17.0.5/babel-webpack/df52bccec1a6f316ea7a61f914ff854a85a49cd504b4c01dbc78fa7fbc1f4c28.json",
        "hash": "17815980436141004006"
      },
      {
        "file": ".angular/cache/17.0.5/babel-webpack/e04c11d17f6eaa6984375d3273e8cae0af2ac58762920e9e161f32fe6e5ed251.json",
        "hash": "16208447823188156664"
      },
      {
        "file": ".angular/cache/17.0.5/babel-webpack/e0631efd1816d70ad97f3897ac91dead3f74ca722a50377727e4df493df95097.json",
        "hash": "4548855696034110752"
      },
      {
        "file": ".angular/cache/17.0.5/babel-webpack/e2068749e92a244de2114025d92de950d2017555d3358fa31a61d3ce76a02d8b.json",
        "hash": "15399260238541112884"
      },
      {
        "file": ".angular/cache/17.0.5/babel-webpack/e403d25a1717fc627f0fb0fdd45dad1fd0cf8dbf22b790b5bd48ec2d5a7d36e4.json",
        "hash": "11357813914920004598"
      },
      {
        "file": ".angular/cache/17.0.5/babel-webpack/e41c3f778b376d3688a8e4615034dbaa233c9b22e868c004fd4632cce909da77.json",
        "hash": "13745060306820329457"
      },
      {
        "file": ".angular/cache/17.0.5/babel-webpack/e4a253d023aee375ca41df663b2799f07287bfa139d97f72a52c801f8daa6a1e.json",
        "hash": "3322328161789828287"
      },
      {
        "file": ".angular/cache/17.0.5/babel-webpack/e4e14da0ac6466d133e8b050c65426a4e82ebaa4dfd6aea34a40fa06e426fb93.json",
        "hash": "6580469995914200094"
      },
      {
        "file": ".angular/cache/17.0.5/babel-webpack/e5c59075436bf742d77c8c872aa87e1b0303f26393ea8586d85e1fbf3dc2e3b7.json",
        "hash": "15352071197639287549"
      },
      {
        "file": ".angular/cache/17.0.5/babel-webpack/e5cdac063c42466e96c17b6fb107b8d93a20e3a99a059e5b43e9aba64a44d1a5.json",
        "hash": "5742906799923193226"
      },
      {
        "file": ".angular/cache/17.0.5/babel-webpack/e67f05208205005815c2f7a13e3a916ee09a778b32486378b01a5adaf65f4393.json",
        "hash": "8333273408681495414"
      },
      {
        "file": ".angular/cache/17.0.5/babel-webpack/e6b4cdf02232e5a3bc4ba19cb8e04482819ddc5d740bba69c1b63175b04c69da.json",
        "hash": "13414444947794368599"
      },
      {
        "file": ".angular/cache/17.0.5/babel-webpack/e7402f13507cdf202afa102d1104fb79716194f5152a7268c99b4ff457e9f9e8.json",
        "hash": "4516919679539422869"
      },
      {
        "file": ".angular/cache/17.0.5/babel-webpack/e7a59bdafb9ed972a9c731adc467d0a8e0fe16f8b7209a2bb141afc6899660bf.json",
        "hash": "7141718852831337359"
      },
      {
        "file": ".angular/cache/17.0.5/babel-webpack/e7ceda654b98a6ab2f217cd6135e4057174eebb55cb529a2206f082dad155981.json",
        "hash": "17191579753295614655"
      },
      {
        "file": ".angular/cache/17.0.5/babel-webpack/e7fff95ea62f525bac821338955e7e6b5ca138d03d1c931377c66d0a4dd13b63.json",
        "hash": "594237727365564750"
      },
      {
        "file": ".angular/cache/17.0.5/babel-webpack/e996d6d088f245787f16be02704c060652f72ffeaa7a5b10779c765b1b40586b.json",
        "hash": "2867927019981165565"
      },
      {
        "file": ".angular/cache/17.0.5/babel-webpack/ea6d4bb976bf545391dfdb401c817936c43dc2928c01d59c1f3f1c0454dedea0.json",
        "hash": "14719978269646317281"
      },
      {
        "file": ".angular/cache/17.0.5/babel-webpack/eaeb61c48c6196186d530b35d2abd7d26d81f626889260c54f05203c3b57b35e.json",
        "hash": "14990929893223650967"
      },
      {
        "file": ".angular/cache/17.0.5/babel-webpack/eaf3e837436ad8af66e57335ebda8000d69cf947316c5625f30e16f98dcea31a.json",
        "hash": "5962137867997391244"
      },
      {
        "file": ".angular/cache/17.0.5/babel-webpack/eb576591cd21948bdde99f8de8dafce72645ff801c4b2f4c65131f985f7f006a.json",
        "hash": "1080262783429731413"
      },
      {
        "file": ".angular/cache/17.0.5/babel-webpack/eb59ad86ef98378bf328c255fd6c649c782e5384f5d1a365f6a5ee23daaec034.json",
        "hash": "12667396376559833806"
      },
      {
        "file": ".angular/cache/17.0.5/babel-webpack/eb621ae25dd5c785b9a6ec311e86e6bbc4675544273b5a22f7121b53a54de5c1.json",
        "hash": "17837407840872989798"
      },
      {
        "file": ".angular/cache/17.0.5/babel-webpack/eba1ae91ddfc8d31e4f8696ec6ce538c47e31ec762dc5efa134cdbe40e8fc8e0.json",
        "hash": "1039757618197852068"
      },
      {
        "file": ".angular/cache/17.0.5/babel-webpack/ebf01653028c28665e3d856bcbe5d5679e8319e30cce5e08a58d5f8139c0195f.json",
        "hash": "18345234732422863977"
      },
      {
        "file": ".angular/cache/17.0.5/babel-webpack/ec476fa0619e7b031817a079d1e4e26b1148216fe8bf8809fa1824c1509f7e9a.json",
        "hash": "11333770575105594098"
      },
      {
        "file": ".angular/cache/17.0.5/babel-webpack/ec6591334cbffe9482a9f2d805b047a4c7fcb56e5b9058bcd842acea8bf9ac33.json",
        "hash": "7322591385139673"
      },
      {
        "file": ".angular/cache/17.0.5/babel-webpack/eca4e06a75b0a5e07932dc5fa40de88693ba8a11d74046822c43090fd5a74b13.json",
        "hash": "16615500824012134015"
      },
      {
        "file": ".angular/cache/17.0.5/babel-webpack/ece4e1bec81d1e07cffbf55656c3bb3063f41c660a262b5d41c2295aa0b5bda4.json",
        "hash": "3295167166421819427"
      },
      {
        "file": ".angular/cache/17.0.5/babel-webpack/eeeea9a50619eba5c9c0d90434bccf134059be7d3d12d2134d3e6d632f0010f7.json",
        "hash": "14653088818658185046"
      },
      {
        "file": ".angular/cache/17.0.5/babel-webpack/ef1d982cfad0bed76f3b1b7113901a1126470141a4db3081b147544b25e1cad7.json",
        "hash": "6821606933793875233"
      },
      {
        "file": ".angular/cache/17.0.5/babel-webpack/efc3d50b6c2292de843264e9a5255fa97dc37862929947d1d379fe7b09f249f5.json",
        "hash": "18007982506212937036"
      },
      {
        "file": ".angular/cache/17.0.5/babel-webpack/eff075cf10e5ad7abe0e1edc078bd61ec4783f8ca894a5a4f42ca45f0c0b53e8.json",
        "hash": "6004481916645888199"
      },
      {
        "file": ".angular/cache/17.0.5/babel-webpack/eff097ff25c52c5904ca5ac4f089b2184b998e041653868dbbc521c87d2efe98.json",
        "hash": "9774993649297393297"
      },
      {
        "file": ".angular/cache/17.0.5/babel-webpack/f05111b451805d71cbe8ef4ac7f429b51469549b8284ceb9295f7a4208adb6a4.json",
        "hash": "7051930128937761464"
      },
      {
        "file": ".angular/cache/17.0.5/babel-webpack/f05e77c58639bbf2a68f75c4ad8cf19cd3a39c7a522a093b7727a56dcfe4f426.json",
        "hash": "12626137164358437948"
      },
      {
        "file": ".angular/cache/17.0.5/babel-webpack/f192ae914cb41a8aa202aac544860e6ff632c7f34523006bcb95593a0a8e453a.json",
        "hash": "13177908442077720765"
      },
      {
        "file": ".angular/cache/17.0.5/babel-webpack/f38cb5b1589a11411c6fc2e2c891d445b78996f5a8391e3323aae491deb2b1ca.json",
        "hash": "10865245068399171894"
      },
      {
        "file": ".angular/cache/17.0.5/babel-webpack/f3fb922abf3627a2058973298007bfbe66ef8216424ebd69e6f9651d101ee159.json",
        "hash": "13202350213982817463"
      },
      {
        "file": ".angular/cache/17.0.5/babel-webpack/f420c0b64beff12f07bdee3a22b40a618b53feedcf316722d453ecd55c075c4e.json",
        "hash": "5500733927791515442"
      },
      {
        "file": ".angular/cache/17.0.5/babel-webpack/f584f04dcf667ecf7deccdc713a5e36d895e0357eaa168c045559ce76024b5d3.json",
        "hash": "2955312339227145336"
      },
      {
        "file": ".angular/cache/17.0.5/babel-webpack/f5e896fb6c9af3b5f2e6d131131545fd4e927414fa297bbc6f7227680375f64a.json",
        "hash": "18387552011158754456"
      },
      {
        "file": ".angular/cache/17.0.5/babel-webpack/f5f3b09477dc639a7cb47da7bb9c9fdddb7cb65b4e0ddcd385389e18c7a6acb9.json",
        "hash": "9957593703534133234"
      },
      {
        "file": ".angular/cache/17.0.5/babel-webpack/f625ae8be160c8363a5472e42acc4d2abfaeba00e657792d900aebe78fca5d43.json",
        "hash": "5654519839940858936"
      },
      {
        "file": ".angular/cache/17.0.5/babel-webpack/f6d27ed52bc91da74b1fab0f527195d06b29d313569c69fcb29d59e62ddfa428.json",
        "hash": "8385580870822368092"
      },
      {
        "file": ".angular/cache/17.0.5/babel-webpack/f7112b09c5309acc1ddc10b9bd1bf353b766b413ba346c261149ac859180496e.json",
        "hash": "6014484194470604044"
      },
      {
        "file": ".angular/cache/17.0.5/babel-webpack/f79419c0dad956c76f1feea69f2cc32e1c8e1e338b1b1f0ae38f72e0463c6c23.json",
        "hash": "12759484725616446972"
      },
      {
        "file": ".angular/cache/17.0.5/babel-webpack/f7c4c71aa6cee3fe9dbcf1a1eabaa077da427fc3d6bf1e47836e99a5104dce60.json",
        "hash": "3049947492056183129"
      },
      {
        "file": ".angular/cache/17.0.5/babel-webpack/f84ded3e49b03291b88c0d81fea6c307df9f885cbcc9ed158b1382571cf6b46e.json",
        "hash": "7257982578603070050"
      },
      {
        "file": ".angular/cache/17.0.5/babel-webpack/f99921be87774d221504a7fbf9ea0699638a1c934aeea309bc53e28888648deb.json",
        "hash": "15263132985607313992"
      },
      {
        "file": ".angular/cache/17.0.5/babel-webpack/fa2bb89cb427074411e3c0ed5673282bb20c3b12692160ca2734d12089ace6ac.json",
        "hash": "1117039615203428059"
      },
      {
        "file": ".angular/cache/17.0.5/babel-webpack/fafc8e5c8a651587c918158bafadd569d85a2eb604cfbc62a3d35e5deb259253.json",
        "hash": "1810642047831480148"
      },
      {
        "file": ".angular/cache/17.0.5/babel-webpack/fb1fe7a8f4ca82ca2eb6e619c6676e9d89be6dc593241fcac6128c245f47af95.json",
        "hash": "1080589068374786148"
      },
      {
        "file": ".angular/cache/17.0.5/babel-webpack/fb635fff00b6619017969dfb902e144a2bdc6c223dc58a1336eab2a273781107.json",
        "hash": "7180745831606533019"
      },
      {
        "file": ".angular/cache/17.0.5/babel-webpack/fbdd82fee4995cb390bfb90a88f1a044ba66370a3ba5abdcda1345aa801c1961.json",
        "hash": "12592299050220865127"
      },
      {
        "file": ".angular/cache/17.0.5/babel-webpack/fc8f8f01bd5a811b11a0999802580575608b834cf7f21cd420069382d7d22b3d.json",
        "hash": "12719570268732493539"
      },
      {
        "file": ".angular/cache/17.0.5/babel-webpack/fcb7d6acd30f53e4c63d2e730032c231b948273533265f2b6b24761edabee53a.json",
        "hash": "10399988101851022446"
      },
      {
        "file": ".angular/cache/17.0.5/babel-webpack/fcd80cd31a26c037249e40a2afd8fb3fffec8eb6bc76a8ab18832d817cc1b5fc.json",
        "hash": "13314980479608384030"
      },
      {
        "file": ".angular/cache/17.0.5/babel-webpack/ff13554d3b89fb3ee8f67154c966871a7d7f852c0ba50639b4b2a2c61a6c621f.json",
        "hash": "16277058958800916020"
      },
      {
        "file": ".angular/cache/17.0.5/babel-webpack/ff19b28711bd9a79cf5c660d24056307819ee857bcff15c08abd7843e6c61814.json",
        "hash": "16796367132559097407"
      },
      {
        "file": ".browserslistrc",
        "hash": "8928530114349553238"
      },
      {
        "file": ".editorconfig",
        "hash": "17241496168097493888"
      },
      {
        "file": ".eslintrc.json",
        "hash": "3555539555184033037"
      },
      {
        "file": ".gitignore",
        "hash": "13924459389979241635"
      },
      {
        "file": ".nx/cache/file-map.json",
        "hash": "8812081465450890156"
      },
      {
        "file": ".nx/cache/lockfile.hash",
        "hash": "3660684754837180888"
      },
      {
        "file": ".nx/cache/parsed-lock-file.json",
        "hash": "16674601807585851791"
      },
      {
        "file": ".nx/cache/project-graph.json",
        "hash": "7718742422986231522"
      },
      {
        "file": ".prettierrc",
        "hash": "10012276632111381719"
      },
      {
        "file": ".vscode/extensions.json",
        "hash": "9820145720478233062"
      },
      {
        "file": ".vscode/settings.json",
        "hash": "14730831395863803542"
      },
      {
        "file": "angular.json",
        "hash": "5962391698463299839"
      },
      {
        "file": "capacitor.config.ts",
        "hash": "11199527040874102992"
      },
      {
        "file": "ionic.config.json",
        "hash": "8630301818635688001"
      },
      {
        "file": "karma.conf.js",
        "hash": "15586218685649057480"
      },
      {
        "file": "package-lock.json",
        "hash": "16439310189846244214"
      },
      {
        "file": "package.json",
        "hash": "6835956306045566606"
      },
      {
        "file": "resources/icon.png",
        "hash": "2667738171922695735"
      },
      {
        "file": "resources/splash.png",
        "hash": "6227508364955791552"
      },
      {
        "file": "src/app/app-routing.module.ts",
        "hash": "12613453600522919792"
      },
      {
        "file": "src/app/app.component.html",
        "hash": "17056000882178073463"
      },
      {
        "file": "src/app/app.component.scss",
        "hash": "3925798864425565485"
      },
      {
        "file": "src/app/app.component.spec.ts",
        "hash": "3680979414714211701"
      },
      {
        "file": "src/app/app.component.ts",
        "hash": "9557523190820870351"
      },
      {
        "file": "src/app/app.module.ts",
        "hash": "14451530340291036043"
      },
      {
        "file": "src/app/components/index.ts",
        "hash": "3132952989506847005"
      },
      {
        "file": "src/app/components/pickup-game-card/pickup-game-card.component.html",
        "hash": "3658224942189570008"
      },
      {
        "file": "src/app/components/pickup-game-card/pickup-game-card.component.scss",
        "hash": "3625768892447802346"
      },
      {
        "file": "src/app/components/pickup-game-card/pickup-game-card.component.ts",
        "hash": "5060764794269216298"
      },
      {
        "file": "src/app/data/index.ts",
        "hash": "9534660136508306868"
      },
      {
        "file": "src/app/data/pickup-game.data.ts",
        "hash": "2689755091643463935"
      },
      {
        "file": "src/app/data/profile.data.ts",
        "hash": "17908760984468317935"
      },
      {
        "file": "src/app/data/sports.data.ts",
        "hash": "12617527106444847680"
      },
      {
        "file": "src/app/data/user.data.ts",
        "hash": "1949035460043256071"
      },
      {
        "file": "src/app/modules/home/home-routing.module.ts",
        "hash": "2479520266805014596"
      },
      {
        "file": "src/app/modules/home/home.component.html",
        "hash": "17369037351891088040"
      },
      {
        "file": "src/app/modules/home/home.component.scss",
        "hash": "3244421341483603138"
      },
      {
        "file": "src/app/modules/home/home.component.ts",
        "hash": "11604551607068827888"
      },
      {
        "file": "src/app/modules/home/home.module.ts",
        "hash": "1991731301352481403"
      },
      {
        "file": "src/app/modules/shared/shared.module.ts",
        "hash": "15058125813162836786"
      },
      {
        "file": "src/app/services/authentication.service.ts",
        "hash": "7774129669674595814"
      },
      {
        "file": "src/app/services/index.ts",
        "hash": "4727309144950271651"
      },
      {
        "file": "src/app/services/profile.service.ts",
        "hash": "11965010133687367179"
      },
      {
        "file": "src/assets/icon/favicon.png",
        "hash": "17482944836898362639"
      },
      {
        "file": "src/assets/shapes.svg",
        "hash": "6713572288142939778"
      },
      {
        "file": "src/environments/environment.prod.ts",
        "hash": "11847377846594200203"
      },
      {
        "file": "src/environments/environment.ts",
        "hash": "14410313991637913761"
      },
      {
        "file": "src/global.scss",
        "hash": "1918626602965251672"
      },
      {
        "file": "src/index.html",
        "hash": "12859993114988254134"
      },
      {
        "file": "src/main.ts",
        "hash": "14418682105238715715"
      },
      {
        "file": "src/polyfills.ts",
        "hash": "6334563476032399242"
      },
      {
        "file": "src/test.ts",
        "hash": "7876741224155508608"
      },
      {
        "file": "src/theme/variables.scss",
        "hash": "9812640960385222337"
      },
      {
        "file": "src/zone-flags.ts",
        "hash": "6117193595888083885"
      },
      {
        "file": "tsconfig.app.json",
        "hash": "7685451593566938896"
      },
      {
        "file": "tsconfig.json",
        "hash": "17285156706200028957"
      },
      {
        "file": "tsconfig.spec.json",
        "hash": "14277469517724802009"
      }
    ]
  }
}
